{
  "categories": {
    "main": [
      {
        "rank": "0",
        "name": "Bitcoin",
        "symbol": "BTC",
        "logo": "",
        "price": "$108111.28",
        "change_1h": "-0.05%",
        "change_24h": "+0.10%",
        "change_7d": "+0.70%",
        "market_cap": "$2,150,126,591,885",
        "volume_24h": "$31,039,354,439",
        "trend_24h": "up",
        "trend_7d": "up"
      },
      {
        "rank": "0",
        "name": "Ethereum",
        "symbol": "ETH",
        "logo": "",
        "price": "$2515.29",
        "change_1h": "+0.26%",
        "change_24h": "+0.61%",
        "change_7d": "+3.21%",
        "market_cap": "$303,638,709,642",
        "volume_24h": "$9,691,100,268",
        "trend_24h": "up",
        "trend_7d": "up"
      },
      {
        "rank": "0",
        "name": "Tether USDt",
        "symbol": "USDT",
        "logo": "",
        "price": "$1.00",
        "change_1h": "-0.01%",
        "change_24h": "+0.01%",
        "change_7d": "+0.01%",
        "market_cap": "$158,647,590,545",
        "volume_24h": "$37,983,991,108",
        "trend_24h": "up",
        "trend_7d": "up"
      },
      {
        "rank": "0",
        "name": "XRP",
        "symbol": "XRP",
        "logo": "",
        "price": "$2.22",
        "change_1h": "+0.22%",
        "change_24h": "-0.11%",
        "change_7d": "+1.30%",
        "market_cap": "$130,889,694,239",
        "volume_24h": "$1,216,572,632",
        "trend_24h": "down",
        "trend_7d": "up"
      },
      {
        "rank": "0",
        "name": "BNB",
        "symbol": "BNB",
        "logo": "",
        "price": "$655.64",
        "change_1h": "+0.09%",
        "change_24h": "+0.39%",
        "change_7d": "+1.07%",
        "market_cap": "$92,370,429,506",
        "volume_24h": "$1,201,619,961",
        "trend_24h": "up",
        "trend_7d": "up"
      },
      {
        "rank": "0",
        "name": "Solana",
        "symbol": "SOL",
        "logo": "",
        "price": "$147.35",
        "change_1h": "+0.12%",
        "change_24h": "+0.12%",
        "change_7d": "-2.39%",
        "market_cap": "$78,811,736,058",
        "volume_24h": "$1,681,572,040",
        "trend_24h": "up",
        "trend_7d": "down"
      },
      {
        "rank": "0",
        "name": "USDC",
        "symbol": "USDC",
        "logo": "",
        "price": "$0.999936",
        "change_1h": "-0.00%",
        "change_24h": "-0.00%",
        "change_7d": "+0.01%",
        "market_cap": "$62,162,725,135",
        "volume_24h": "$3,763,323,550",
        "trend_24h": "down",
        "trend_7d": "up"
      },
      {
        "rank": "0",
        "name": "TRON",
        "symbol": "TRX",
        "logo": "",
        "price": "$0.283298",
        "change_1h": "-0.23%",
        "change_24h": "-0.10%",
        "change_7d": "+3.17%",
        "market_cap": "$26,851,703,244",
        "volume_24h": "$293,959,691",
        "trend_24h": "down",
        "trend_7d": "up"
      },
      {
        "rank": "0",
        "name": "Dogecoin",
        "symbol": "DOGE",
        "logo": "",
        "price": "$0.164275",
        "change_1h": "+0.02%",
        "change_24h": "+0.87%",
        "change_7d": "-0.01%",
        "market_cap": "$24,637,097,141",
        "volume_24h": "$485,996,297",
        "trend_24h": "up",
        "trend_7d": "down"
      },
      {
        "rank": "0",
        "name": "Cardano",
        "symbol": "ADA",
        "logo": "",
        "price": "$0.574893",
        "change_1h": "+0.02%",
        "change_24h": "+0.51%",
        "change_7d": "+1.60%",
        "market_cap": "$20,342,029,528",
        "volume_24h": "$324,312,265",
        "trend_24h": "up",
        "trend_7d": "up"
      },
      {
        "rank": "0",
        "name": "Hyperliquid",
        "symbol": "HYPE",
        "logo": "",
        "price": "$39.01",
        "change_1h": "+0.39%",
        "change_24h": "+0.85%",
        "change_7d": "+3.32%",
        "market_cap": "$13,025,975,623",
        "volume_24h": "$153,250,313",
        "trend_24h": "up",
        "trend_7d": "up"
      },
      {
        "rank": "0",
        "name": "Sui",
        "symbol": "SUI",
        "logo": "",
        "price": "$2.90",
        "change_1h": "+0.05%",
        "change_24h": "+0.79%",
        "change_7d": "+3.48%",
        "market_cap": "$10,008,151,189",
        "volume_24h": "$473,159,571",
        "trend_24h": "up",
        "trend_7d": "up"
      },
      {
        "rank": "0",
        "name": "Bitcoin Cash",
        "symbol": "BCH",
        "logo": "",
        "price": "$486.96",
        "change_1h": "+0.29%",
        "change_24h": "+0.23%",
        "change_7d": "-0.87%",
        "market_cap": "$9,687,183,546",
        "volume_24h": "$260,368,337",
        "trend_24h": "up",
        "trend_7d": "down"
      },
      {
        "rank": "0",
        "name": "Chainlink",
        "symbol": "LINK",
        "logo": "",
        "price": "$13.19",
        "change_1h": "+0.05%",
        "change_24h": "+0.61%",
        "change_7d": "-1.52%",
        "market_cap": "$8,945,632,828",
        "volume_24h": "$157,646,825",
        "trend_24h": "up",
        "trend_7d": "down"
      },
      {
        "rank": "0",
        "name": "Avalanche",
        "symbol": "AVAX",
        "logo": "",
        "price": "$17.87",
        "change_1h": "-0.12%",
        "change_24h": "+0.62%",
        "change_7d": "-0.56%",
        "market_cap": "$7,546,670,261",
        "volume_24h": "$118,782,320",
        "trend_24h": "up",
        "trend_7d": "down"
      },
      {
        "rank": "0",
        "name": "Stellar",
        "symbol": "XLM",
        "logo": "",
        "price": "$0.237411",
        "change_1h": "+0.30%",
        "change_24h": "-0.32%",
        "change_7d": "-0.86%",
        "market_cap": "$7,344,413,681",
        "volume_24h": "$61,400,946",
        "trend_24h": "down",
        "trend_7d": "down"
      },
      {
        "rank": "0",
        "name": "Toncoin",
        "symbol": "TON",
        "logo": "",
        "price": "$2.76",
        "change_1h": "+0.27%",
        "change_24h": "+0.04%",
        "change_7d": "-3.51%",
        "market_cap": "$6,800,831,694",
        "volume_24h": "$84,930,997",
        "trend_24h": "up",
        "trend_7d": "down"
      },
      {
        "rank": "0",
        "name": "Shiba Inu",
        "symbol": "SHIB",
        "logo": "",
        "price": "$0.000011",
        "change_1h": "+0.03%",
        "change_24h": "+0.51%",
        "change_7d": "-0.94%",
        "market_cap": "$6,747,221,725",
        "volume_24h": "$74,234,401",
        "trend_24h": "up",
        "trend_7d": "down"
      },
      {
        "rank": "0",
        "name": "Litecoin",
        "symbol": "LTC",
        "logo": "",
        "price": "$87.32",
        "change_1h": "-0.22%",
        "change_24h": "+0.92%",
        "change_7d": "+1.24%",
        "market_cap": "$6,639,952,499",
        "volume_24h": "$249,727,325",
        "trend_24h": "up",
        "trend_7d": "up"
      },
      {
        "rank": "0",
        "name": "Hedera",
        "symbol": "HBAR",
        "logo": "",
        "price": "$0.154681",
        "change_1h": "-0.07%",
        "change_24h": "+0.89%",
        "change_7d": "+4.21%",
        "market_cap": "$6,557,129,200",
        "volume_24h": "$125,587,030",
        "trend_24h": "up",
        "trend_7d": "up"
      },
      {
        "rank": "0",
        "name": "Monero",
        "symbol": "XMR",
        "logo": "",
        "price": "$314.58",
        "change_1h": "-0.06%",
        "change_24h": "+0.24%",
        "change_7d": "+2.33%",
        "market_cap": "$5,803,028,429",
        "volume_24h": "$57,215,348",
        "trend_24h": "up",
        "trend_7d": "up"
      },
      {
        "rank": "0",
        "name": "Dai",
        "symbol": "DAI",
        "logo": "",
        "price": "$0.999923",
        "change_1h": "-0.01%",
        "change_24h": "-0.01%",
        "change_7d": "+0.01%",
        "market_cap": "$5,364,967,261",
        "volume_24h": "$18,429,079,784",
        "trend_24h": "down",
        "trend_7d": "up"
      },
      {
        "rank": "0",
        "name": "Polkadot",
        "symbol": "DOT",
        "logo": "",
        "price": "$3.35",
        "change_1h": "-0.01%",
        "change_24h": "-0.20%",
        "change_7d": "-1.88%",
        "market_cap": "$5,339,295,996",
        "volume_24h": "$107,143,460",
        "trend_24h": "down",
        "trend_7d": "down"
      },
      {
        "rank": "0",
        "name": "Ethena USDe",
        "symbol": "USDe",
        "logo": "",
        "price": "$1.00",
        "change_1h": "-0.01%",
        "change_24h": "+0.02%",
        "change_7d": "+0.02%",
        "market_cap": "$5,308,048,249",
        "volume_24h": "$69,333,958",
        "trend_24h": "up",
        "trend_7d": "up"
      },
      {
        "rank": "0",
        "name": "Uniswap",
        "symbol": "UNI",
        "logo": "",
        "price": "$7.02",
        "change_1h": "-0.25%",
        "change_24h": "+1.61%",
        "change_7d": "-1.66%",
        "market_cap": "$4,415,055,723",
        "volume_24h": "$239,227,878",
        "trend_24h": "up",
        "trend_7d": "down"
      },
      {
        "rank": "0",
        "name": "Aave",
        "symbol": "AAVE",
        "logo": "",
        "price": "$274.00",
        "change_1h": "+0.32%",
        "change_24h": "+3.80%",
        "change_7d": "+5.83%",
        "market_cap": "$4,158,118,637",
        "volume_24h": "$252,393,600",
        "trend_24h": "up",
        "trend_7d": "up"
      },
      {
        "rank": "0",
        "name": "Pepe",
        "symbol": "PEPE",
        "logo": "",
        "price": "$0.000010",
        "change_1h": "+0.04%",
        "change_24h": "+0.84%",
        "change_7d": "+1.39%",
        "market_cap": "$4,071,533,443",
        "volume_24h": "$427,949,094",
        "trend_24h": "up",
        "trend_7d": "up"
      },
      {
        "rank": "0",
        "name": "Bittensor",
        "symbol": "TAO",
        "logo": "",
        "price": "$321.95",
        "change_1h": "+0.47%",
        "change_24h": "-0.70%",
        "change_7d": "-2.92%",
        "market_cap": "$2,886,878,517",
        "volume_24h": "$63,476,308",
        "trend_24h": "down",
        "trend_7d": "down"
      },
      {
        "rank": "0",
        "name": "Aptos",
        "symbol": "APT",
        "logo": "",
        "price": "$4.41",
        "change_1h": "-0.20%",
        "change_24h": "+0.18%",
        "change_7d": "-8.56%",
        "market_cap": "$2,845,651,372",
        "volume_24h": "$71,817,994",
        "trend_24h": "up",
        "trend_7d": "down"
      },
      {
        "rank": "0",
        "name": "NEAR Protocol",
        "symbol": "NEAR",
        "logo": "",
        "price": "$2.14",
        "change_1h": "+0.09%",
        "change_24h": "+0.82%",
        "change_7d": "-1.10%",
        "market_cap": "$2,634,907,313",
        "volume_24h": "$83,204,038",
        "trend_24h": "up",
        "trend_7d": "down"
      },
      {
        "rank": "0",
        "name": "Ondo",
        "symbol": "ONDO",
        "logo": "",
        "price": "$0.781324",
        "change_1h": "+0.36%",
        "change_24h": "+0.75%",
        "change_7d": "+2.57%",
        "market_cap": "$2,468,285,846",
        "volume_24h": "$62,966,316",
        "trend_24h": "up",
        "trend_7d": "up"
      },
      {
        "rank": "0",
        "name": "World Liberty Financial USD",
        "symbol": "USD1",
        "logo": "",
        "price": "$1.00",
        "change_1h": "-0.00%",
        "change_24h": "-0.00%",
        "change_7d": "+0.03%",
        "market_cap": "$2,204,303,289",
        "volume_24h": "$668,910,440",
        "trend_24h": "down",
        "trend_7d": "up"
      },
      {
        "rank": "0",
        "name": "POL (prev. MATIC)",
        "symbol": "POL",
        "logo": "",
        "price": "$0.182639",
        "change_1h": "-0.11%",
        "change_24h": "+2.04%",
        "change_7d": "+2.64%",
        "market_cap": "$1,910,205,490",
        "volume_24h": "$87,843,690",
        "trend_24h": "up",
        "trend_7d": "up"
      },
      {
        "rank": "0",
        "name": "Mantle",
        "symbol": "MNT",
        "logo": "",
        "price": "$0.563601",
        "change_1h": "+0.00%",
        "change_24h": "+0.05%",
        "change_7d": "-7.25%",
        "market_cap": "$1,896,964,019",
        "volume_24h": "$173,459,326",
        "trend_24h": "up",
        "trend_7d": "down"
      },
      {
        "rank": "0",
        "name": "OFFICIAL TRUMP",
        "symbol": "TRUMP",
        "logo": "",
        "price": "$8.54",
        "change_1h": "-0.01%",
        "change_24h": "+0.21%",
        "change_7d": "-6.23%",
        "market_cap": "$1,707,193,132",
        "volume_24h": "$110,520,496",
        "trend_24h": "up",
        "trend_7d": "down"
      },
      {
        "rank": "0",
        "name": "Arbitrum",
        "symbol": "ARB",
        "logo": "",
        "price": "$0.326559",
        "change_1h": "+0.58%",
        "change_24h": "+1.58%",
        "change_7d": "+5.45%",
        "market_cap": "$1,620,788,322",
        "volume_24h": "$125,562,197",
        "trend_24h": "up",
        "trend_7d": "up"
      },
      {
        "rank": "0",
        "name": "Ethena",
        "symbol": "ENA",
        "logo": "",
        "price": "$0.254562",
        "change_1h": "+0.14%",
        "change_24h": "+0.76%",
        "change_7d": "-3.96%",
        "market_cap": "$1,617,659,362",
        "volume_24h": "$74,587,093",
        "trend_24h": "up",
        "trend_7d": "down"
      },
      {
        "rank": "0",
        "name": "Artificial Superintelligence Alliance",
        "symbol": "FET",
        "logo": "",
        "price": "$0.660987",
        "change_1h": "-0.27%",
        "change_24h": "-2.23%",
        "change_7d": "-3.66%",
        "market_cap": "$1,581,490,026",
        "volume_24h": "$71,995,479",
        "trend_24h": "down",
        "trend_7d": "down"
      },
      {
        "rank": "0",
        "name": "Cosmos",
        "symbol": "ATOM",
        "logo": "",
        "price": "$4.00",
        "change_1h": "+0.15%",
        "change_24h": "+0.16%",
        "change_7d": "+0.17%",
        "market_cap": "$1,565,475,808",
        "volume_24h": "$54,585,397",
        "trend_24h": "up",
        "trend_7d": "up"
      },
      {
        "rank": "0",
        "name": "Filecoin",
        "symbol": "FIL",
        "logo": "",
        "price": "$2.25",
        "change_1h": "+0.10%",
        "change_24h": "-0.06%",
        "change_7d": "-1.09%",
        "market_cap": "$1,530,520,454",
        "volume_24h": "$111,493,337",
        "trend_24h": "down",
        "trend_7d": "down"
      },
      {
        "rank": "0",
        "name": "Bonk",
        "symbol": "BONK",
        "logo": "",
        "price": "$0.000018",
        "change_1h": "+0.85%",
        "change_24h": "+8.98%",
        "change_7d": "+25.46%",
        "market_cap": "$1,476,161,183",
        "volume_24h": "$644,323,594",
        "trend_24h": "up",
        "trend_7d": "up"
      },
      {
        "rank": "0",
        "name": "First Digital USD",
        "symbol": "FDUSD",
        "logo": "",
        "price": "$0.998058",
        "change_1h": "-0.02%",
        "change_24h": "-0.02%",
        "change_7d": "-0.02%",
        "market_cap": "$1,469,592,503",
        "volume_24h": "$2,161,358,978",
        "trend_24h": "down",
        "trend_7d": "down"
      },
      {
        "rank": "0",
        "name": "Worldcoin",
        "symbol": "WLD",
        "logo": "",
        "price": "$0.865555",
        "change_1h": "-0.20%",
        "change_24h": "-0.80%",
        "change_7d": "-3.35%",
        "market_cap": "$1,465,280,690",
        "volume_24h": "$85,492,605",
        "trend_24h": "down",
        "trend_7d": "down"
      },
      {
        "rank": "0",
        "name": "Sei",
        "symbol": "SEI",
        "logo": "",
        "price": "$0.262208",
        "change_1h": "-0.80%",
        "change_24h": "+0.83%",
        "change_7d": "-8.09%",
        "market_cap": "$1,457,075,021",
        "volume_24h": "$107,230,806",
        "trend_24h": "up",
        "trend_7d": "down"
      },
      {
        "rank": "0",
        "name": "Fartcoin",
        "symbol": "FARTCOIN",
        "logo": "",
        "price": "$1.18",
        "change_1h": "-0.09%",
        "change_24h": "+0.79%",
        "change_7d": "+8.71%",
        "market_cap": "$1,177,430,340",
        "volume_24h": "$86,365,694",
        "trend_24h": "up",
        "trend_7d": "up"
      },
      {
        "rank": "0",
        "name": "Injective",
        "symbol": "INJ",
        "logo": "",
        "price": "$10.57",
        "change_1h": "+0.14%",
        "change_24h": "-2.49%",
        "change_7d": "-3.44%",
        "market_cap": "$1,056,864,629",
        "volume_24h": "$67,598,646",
        "trend_24h": "down",
        "trend_7d": "down"
      },
      {
        "rank": "0",
        "name": "Celestia",
        "symbol": "TIA",
        "logo": "",
        "price": "$1.48",
        "change_1h": "+0.24%",
        "change_24h": "-2.31%",
        "change_7d": "+0.21%",
        "market_cap": "$1,035,606,632",
        "volume_24h": "$88,783,619",
        "trend_24h": "down",
        "trend_7d": "up"
      },
      {
        "rank": "0",
        "name": "Virtuals Protocol",
        "symbol": "VIRTUAL",
        "logo": "",
        "price": "$1.54",
        "change_1h": "+0.26%",
        "change_24h": "-0.69%",
        "change_7d": "+0.57%",
        "market_cap": "$1,006,900,155",
        "volume_24h": "$137,803,515",
        "trend_24h": "down",
        "trend_7d": "up"
      },
      {
        "rank": "0",
        "name": "Pudgy Penguins",
        "symbol": "PENGU",
        "logo": "",
        "price": "$0.015663",
        "change_1h": "+1.02%",
        "change_24h": "-3.89%",
        "change_7d": "+8.93%",
        "market_cap": "$984,606,364",
        "volume_24h": "$296,392,558",
        "trend_24h": "down",
        "trend_7d": "up"
      },
      {
        "rank": "0",
        "name": "Optimism",
        "symbol": "OP",
        "logo": "",
        "price": "$0.529445",
        "change_1h": "+0.37%",
        "change_24h": "-0.36%",
        "change_7d": "-3.99%",
        "market_cap": "$927,687,012",
        "volume_24h": "$82,379,810",
        "trend_24h": "down",
        "trend_7d": "down"
      },
      {
        "rank": "0",
        "name": "dogwifhat",
        "symbol": "WIF",
        "logo": "",
        "price": "$0.835905",
        "change_1h": "+0.12%",
        "change_24h": "+0.08%",
        "change_7d": "-0.14%",
        "market_cap": "$834,935,963",
        "volume_24h": "$274,032,469",
        "trend_24h": "up",
        "trend_7d": "down"
      },
      {
        "rank": "0",
        "name": "Curve DAO Token",
        "symbol": "CRV",
        "logo": "",
        "price": "$0.497556",
        "change_1h": "-0.05%",
        "change_24h": "-0.51%",
        "change_7d": "-3.11%",
        "market_cap": "$677,223,116",
        "volume_24h": "$56,676,990",
        "trend_24h": "down",
        "trend_7d": "down"
      },
      {
        "rank": "0",
        "name": "Maple Finance",
        "symbol": "SYRUP",
        "logo": "",
        "price": "$0.550541",
        "change_1h": "+0.07%",
        "change_24h": "+3.40%",
        "change_7d": "-8.09%",
        "market_cap": "$654,919,360",
        "volume_24h": "$68,460,467",
        "trend_24h": "up",
        "trend_7d": "down"
      },
      {
        "rank": "0",
        "name": "Zcash",
        "symbol": "ZEC",
        "logo": "",
        "price": "$39.10",
        "change_1h": "+0.08%",
        "change_24h": "-2.74%",
        "change_7d": "+0.39%",
        "market_cap": "$654,343,016",
        "volume_24h": "$86,234,570",
        "trend_24h": "down",
        "trend_7d": "up"
      },
      {
        "rank": "0",
        "name": "Gala",
        "symbol": "GALA",
        "logo": "",
        "price": "$0.013889",
        "change_1h": "+0.45%",
        "change_24h": "+0.39%",
        "change_7d": "-0.61%",
        "market_cap": "$627,107,681",
        "volume_24h": "$55,154,915",
        "trend_24h": "up",
        "trend_7d": "down"
      },
      {
        "rank": "0",
        "name": "AB",
        "symbol": "AB",
        "logo": "",
        "price": "$0.008126",
        "change_1h": "+0.08%",
        "change_24h": "+1.33%",
        "change_7d": "-1.86%",
        "market_cap": "$538,557,157",
        "volume_24h": "$55,529,820",
        "trend_24h": "up",
        "trend_7d": "down"
      },
      {
        "rank": "0",
        "name": "Bitcoin SV",
        "symbol": "BSV",
        "logo": "",
        "price": "$24.10",
        "change_1h": "+0.27%",
        "change_24h": "+2.68%",
        "change_7d": "-21.71%",
        "market_cap": "$479,232,754",
        "volume_24h": "$67,442,355",
        "trend_24h": "up",
        "trend_7d": "down"
      },
      {
        "rank": "0",
        "name": "Livepeer",
        "symbol": "LPT",
        "logo": "",
        "price": "$6.22",
        "change_1h": "-0.22%",
        "change_24h": "+4.66%",
        "change_7d": "+5.40%",
        "market_cap": "$261,988,617",
        "volume_24h": "$111,601,510",
        "trend_24h": "up",
        "trend_7d": "up"
      },
      {
        "rank": "0",
        "name": "Safe",
        "symbol": "SAFE",
        "logo": "",
        "price": "$0.419502",
        "change_1h": "+0.85%",
        "change_24h": "+5.65%",
        "change_7d": "+4.04%",
        "market_cap": "$254,651,178",
        "volume_24h": "$52,141,441",
        "trend_24h": "up",
        "trend_7d": "up"
      },
      {
        "rank": "0",
        "name": "Peanut the Squirrel",
        "symbol": "PNUT",
        "logo": "",
        "price": "$0.221186",
        "change_1h": "+0.52%",
        "change_24h": "-1.26%",
        "change_7d": "-0.70%",
        "market_cap": "$221,153,014",
        "volume_24h": "$81,632,552",
        "trend_24h": "down",
        "trend_7d": "down"
      },
      {
        "rank": "0",
        "name": "Moo Deng (moodengsol.com)",
        "symbol": "MOODENG",
        "logo": "",
        "price": "$0.183888",
        "change_1h": "+1.55%",
        "change_24h": "+4.95%",
        "change_7d": "+24.08%",
        "market_cap": "$182,043,909",
        "volume_24h": "$158,454,763",
        "trend_24h": "up",
        "trend_7d": "up"
      },
      {
        "rank": "0",
        "name": "Neiro (First Neiro On Ethereum)",
        "symbol": "NEIRO",
        "logo": "",
        "price": "$0.000419",
        "change_1h": "+0.53%",
        "change_24h": "-3.27%",
        "change_7d": "+12.44%",
        "market_cap": "$176,088,139",
        "volume_24h": "$80,263,496",
        "trend_24h": "down",
        "trend_7d": "up"
      },
      {
        "rank": "0",
        "name": "ai16z",
        "symbol": "AI16Z",
        "logo": "",
        "price": "$0.151787",
        "change_1h": "-0.26%",
        "change_24h": "+1.55%",
        "change_7d": "+3.50%",
        "market_cap": "$166,965,873",
        "volume_24h": "$99,592,942",
        "trend_24h": "up",
        "trend_7d": "up"
      },
      {
        "rank": "0",
        "name": "Fasttoken",
        "symbol": "FTN",
        "logo": "",
        "price": "$4.44",
        "change_1h": "-0.02%",
        "change_24h": "-0.01%",
        "change_7d": "+0.67%",
        "market_cap": "$1,938,297,019",
        "volume_24h": "$56,668,017",
        "trend_24h": "down",
        "trend_7d": "up"
      },
      {
        "rank": "0",
        "name": "Sahara AI",
        "symbol": "SAHARA",
        "logo": "",
        "price": "$0.081099",
        "change_1h": "+0.27%",
        "change_24h": "-1.03%",
        "change_7d": "-7.68%",
        "market_cap": "$165,441,327",
        "volume_24h": "$89,458,974",
        "trend_24h": "down",
        "trend_7d": "down"
      },
      {
        "rank": "0",
        "name": "48 Club Token",
        "symbol": "KOGE",
        "logo": "",
        "price": "$48.01",
        "change_1h": "-0.01%",
        "change_24h": "-0.02%",
        "change_7d": "+0.00%",
        "market_cap": "$162,668,416",
        "volume_24h": "$639,071,950",
        "trend_24h": "down",
        "trend_7d": "up"
      },
      {
        "rank": "0",
        "name": "Humanity Protocol",
        "symbol": "H",
        "logo": "",
        "price": "$0.081386",
        "change_1h": "+4.53%",
        "change_24h": "-20.18%",
        "change_7d": "+282.73%",
        "market_cap": "$148,529,706",
        "volume_24h": "$252,089,744",
        "trend_24h": "down",
        "trend_7d": "up"
      },
      {
        "rank": "0",
        "name": "FUNToken",
        "symbol": "FUN",
        "logo": "",
        "price": "$0.013453",
        "change_1h": "+0.67%",
        "change_24h": "-0.87%",
        "change_7d": "+34.76%",
        "market_cap": "$145,538,396",
        "volume_24h": "$76,362,063",
        "trend_24h": "down",
        "trend_7d": "up"
      },
      {
        "rank": "0",
        "name": "AUSD",
        "symbol": "AUSD",
        "logo": "",
        "price": "$0.999811",
        "change_1h": "+0.00%",
        "change_24h": "-0.01%",
        "change_7d": "+0.01%",
        "market_cap": "$128,881,501",
        "volume_24h": "$56,344,135",
        "trend_24h": "down",
        "trend_7d": "up"
      },
      {
        "rank": "0",
        "name": "aixbt",
        "symbol": "AIXBT",
        "logo": "",
        "price": "$0.130331",
        "change_1h": "+0.09%",
        "change_24h": "+3.65%",
        "change_7d": "-2.90%",
        "market_cap": "$123,263,659",
        "volume_24h": "$60,523,623",
        "trend_24h": "up",
        "trend_7d": "down"
      },
      {
        "rank": "0",
        "name": "Stratis [New]",
        "symbol": "STRAX",
        "logo": "",
        "price": "$0.050098",
        "change_1h": "-0.17%",
        "change_24h": "+4.41%",
        "change_7d": "+15.99%",
        "market_cap": "$99,280,560",
        "volume_24h": "$58,398,332",
        "trend_24h": "up",
        "trend_7d": "up"
      },
      {
        "rank": "0",
        "name": "Velo",
        "symbol": "VELO",
        "logo": "",
        "price": "$0.013389",
        "change_1h": "+0.34%",
        "change_24h": "-1.90%",
        "change_7d": "-0.32%",
        "market_cap": "$98,947,639",
        "volume_24h": "$117,457,746",
        "trend_24h": "down",
        "trend_7d": "down"
      },
      {
        "rank": "0",
        "name": "CARV",
        "symbol": "CARV",
        "logo": "",
        "price": "$0.295334",
        "change_1h": "-1.38%",
        "change_24h": "+14.40%",
        "change_7d": "+24.93%",
        "market_cap": "$86,661,519",
        "volume_24h": "$341,769,740",
        "trend_24h": "up",
        "trend_7d": "up"
      },
      {
        "rank": "0",
        "name": "Newton Protocol",
        "symbol": "NEWT",
        "logo": "",
        "price": "$0.326313",
        "change_1h": "-0.30%",
        "change_24h": "-2.97%",
        "change_7d": "-16.39%",
        "market_cap": "$70,157,288",
        "volume_24h": "$206,678,003",
        "trend_24h": "down",
        "trend_7d": "down"
      },
      {
        "rank": "0",
        "name": "EGL1",
        "symbol": "EGL1",
        "logo": "",
        "price": "$0.068648",
        "change_1h": "-3.43%",
        "change_24h": "-14.43%",
        "change_7d": "-0.35%",
        "market_cap": "$68,648,476",
        "volume_24h": "$121,032,138",
        "trend_24h": "down",
        "trend_7d": "down"
      },
      {
        "rank": "0",
        "name": "Huma Finance",
        "symbol": "HUMA",
        "logo": "",
        "price": "$0.030913",
        "change_1h": "+0.82%",
        "change_24h": "-1.23%",
        "change_7d": "-6.25%",
        "market_cap": "$53,582,977",
        "volume_24h": "$63,652,924",
        "trend_24h": "down",
        "trend_7d": "down"
      },
      {
        "rank": "0",
        "name": "Seraph",
        "symbol": "SERAPH",
        "logo": "",
        "price": "$0.194367",
        "change_1h": "+0.53%",
        "change_24h": "+1.31%",
        "change_7d": "+2.45%",
        "market_cap": "$46,551,601",
        "volume_24h": "$82,886,339",
        "trend_24h": "up",
        "trend_7d": "up"
      },
      {
        "rank": "0",
        "name": "Strike",
        "symbol": "STRK",
        "logo": "",
        "price": "$7.85",
        "change_1h": "+2.89%",
        "change_24h": "-5.05%",
        "change_7d": "+36.47%",
        "market_cap": "$44,013,838",
        "volume_24h": "$69,830,065",
        "trend_24h": "down",
        "trend_7d": "up"
      },
      {
        "rank": "0",
        "name": "Impossible Cloud Network",
        "symbol": "ICNT",
        "logo": "",
        "price": "$0.244057",
        "change_1h": "+3.15%",
        "change_24h": "-6.05%",
        "change_7d": "-59.88%",
        "market_cap": "$40,812,662",
        "volume_24h": "$52,102,096",
        "trend_24h": "down",
        "trend_7d": "down"
      },
      {
        "rank": "0",
        "name": "Roam",
        "symbol": "ROAM",
        "logo": "",
        "price": "$0.124120",
        "change_1h": "+0.31%",
        "change_24h": "-8.84%",
        "change_7d": "-11.73%",
        "market_cap": "$37,468,799",
        "volume_24h": "$77,727,759",
        "trend_24h": "down",
        "trend_7d": "down"
      },
      {
        "rank": "0",
        "name": "GUNZ",
        "symbol": "GUN",
        "logo": "",
        "price": "$0.035852",
        "change_1h": "-0.67%",
        "change_24h": "+12.52%",
        "change_7d": "+55.29%",
        "market_cap": "$34,220,853",
        "volume_24h": "$75,262,777",
        "trend_24h": "up",
        "trend_7d": "up"
      },
      {
        "rank": "0",
        "name": "Bubblemaps",
        "symbol": "BMT",
        "logo": "",
        "price": "$0.087909",
        "change_1h": "+1.65%",
        "change_24h": "-34.69%",
        "change_7d": "-36.36%",
        "market_cap": "$31,636,470",
        "volume_24h": "$157,699,116",
        "trend_24h": "down",
        "trend_7d": "down"
      },
      {
        "rank": "0",
        "name": "Bedrock",
        "symbol": "BR",
        "logo": "",
        "price": "$0.128044",
        "change_1h": "+0.01%",
        "change_24h": "+0.02%",
        "change_7d": "+60.80%",
        "market_cap": "$26,889,321",
        "volume_24h": "$4,276,208,950",
        "trend_24h": "up",
        "trend_7d": "up"
      },
      {
        "rank": "0",
        "name": "Bulla",
        "symbol": "BULLA",
        "logo": "",
        "price": "$0.072511",
        "change_1h": "+0.51%",
        "change_24h": "-4.91%",
        "change_7d": "-34.06%",
        "market_cap": "$20,303,172",
        "volume_24h": "$84,573,343",
        "trend_24h": "down",
        "trend_7d": "down"
      },
      {
        "rank": "0",
        "name": "Hifi Finance",
        "symbol": "HIFI",
        "logo": "",
        "price": "$0.084079",
        "change_1h": "-3.18%",
        "change_24h": "-35.59%",
        "change_7d": "-34.15%",
        "market_cap": "$11,923,824",
        "volume_24h": "$60,421,613",
        "trend_24h": "down",
        "trend_7d": "down"
      },
      {
        "rank": "0",
        "name": "Quq",
        "symbol": "QUQ",
        "logo": "",
        "price": "$0.002755",
        "change_1h": "+0.01%",
        "change_24h": "+0.00%",
        "change_7d": "-0.01%",
        "market_cap": "$2,755,480",
        "volume_24h": "$232,076,977",
        "trend_24h": "up",
        "trend_7d": "down"
      },
      {
        "rank": "0",
        "name": "StormX",
        "symbol": "STMX",
        "logo": "",
        "price": "$0.000117",
        "change_1h": "+2.39%",
        "change_24h": "+26.10%",
        "change_7d": "-91.36%",
        "market_cap": "$1,451,053",
        "volume_24h": "$366,522,156",
        "trend_24h": "up",
        "trend_7d": "down"
      },
      {
        "rank": "0",
        "name": "Tether USD Bridged ZED20",
        "symbol": "USDT.z",
        "logo": "",
        "price": "$1.00",
        "change_1h": "+0.01%",
        "change_24h": "+0.00%",
        "change_7d": "+0.02%",
        "market_cap": "$0",
        "volume_24h": "$63,926,019",
        "trend_24h": "up",
        "trend_7d": "up"
      },
      {
        "rank": "0",
        "name": "Wayfinder",
        "symbol": "PROMPT",
        "logo": "",
        "price": "$0.119313",
        "change_1h": "+0.19%",
        "change_24h": "-8.96%",
        "change_7d": "-12.53%",
        "market_cap": "$0",
        "volume_24h": "$51,689,877",
        "trend_24h": "down",
        "trend_7d": "down"
      }
    ],
    "top_gainers_24h": [
      {
        "rank": "0",
        "name": "StormX",
        "symbol": "STMX",
        "logo": "",
        "price": "$0.000117",
        "change_1h": "+2.39%",
        "change_24h": "+26.10%",
        "change_7d": "-91.36%",
        "market_cap": "$1,451,053",
        "volume_24h": "$366,522,156",
        "trend_24h": "up",
        "trend_7d": "down",
        "change_class": "positive"
      },
      {
        "rank": "0",
        "name": "CARV",
        "symbol": "CARV",
        "logo": "",
        "price": "$0.295334",
        "change_1h": "-1.38%",
        "change_24h": "+14.40%",
        "change_7d": "+24.93%",
        "market_cap": "$86,661,519",
        "volume_24h": "$341,769,740",
        "trend_24h": "up",
        "trend_7d": "up",
        "change_class": "positive"
      },
      {
        "rank": "0",
        "name": "GUNZ",
        "symbol": "GUN",
        "logo": "",
        "price": "$0.035852",
        "change_1h": "-0.67%",
        "change_24h": "+12.52%",
        "change_7d": "+55.29%",
        "market_cap": "$34,220,853",
        "volume_24h": "$75,262,777",
        "trend_24h": "up",
        "trend_7d": "up",
        "change_class": "positive"
      },
      {
        "rank": "0",
        "name": "Bonk",
        "symbol": "BONK",
        "logo": "",
        "price": "$0.000018",
        "change_1h": "+0.85%",
        "change_24h": "+8.98%",
        "change_7d": "+25.46%",
        "market_cap": "$1,476,161,183",
        "volume_24h": "$644,323,594",
        "trend_24h": "up",
        "trend_7d": "up",
        "change_class": "positive"
      },
      {
        "rank": "0",
        "name": "Safe",
        "symbol": "SAFE",
        "logo": "",
        "price": "$0.419502",
        "change_1h": "+0.85%",
        "change_24h": "+5.65%",
        "change_7d": "+4.04%",
        "market_cap": "$254,651,178",
        "volume_24h": "$52,141,441",
        "trend_24h": "up",
        "trend_7d": "up",
        "change_class": "positive"
      },
      {
        "rank": "0",
        "name": "Moo Deng (moodengsol.com)",
        "symbol": "MOODENG",
        "logo": "",
        "price": "$0.183888",
        "change_1h": "+1.55%",
        "change_24h": "+4.95%",
        "change_7d": "+24.08%",
        "market_cap": "$182,043,909",
        "volume_24h": "$158,454,763",
        "trend_24h": "up",
        "trend_7d": "up",
        "change_class": "positive"
      },
      {
        "rank": "0",
        "name": "Livepeer",
        "symbol": "LPT",
        "logo": "",
        "price": "$6.22",
        "change_1h": "-0.22%",
        "change_24h": "+4.66%",
        "change_7d": "+5.40%",
        "market_cap": "$261,988,617",
        "volume_24h": "$111,601,510",
        "trend_24h": "up",
        "trend_7d": "up",
        "change_class": "positive"
      },
      {
        "rank": "0",
        "name": "Stratis [New]",
        "symbol": "STRAX",
        "logo": "",
        "price": "$0.050098",
        "change_1h": "-0.17%",
        "change_24h": "+4.41%",
        "change_7d": "+15.99%",
        "market_cap": "$99,280,560",
        "volume_24h": "$58,398,332",
        "trend_24h": "up",
        "trend_7d": "up",
        "change_class": "positive"
      },
      {
        "rank": "0",
        "name": "Aave",
        "symbol": "AAVE",
        "logo": "",
        "price": "$274.00",
        "change_1h": "+0.32%",
        "change_24h": "+3.80%",
        "change_7d": "+5.83%",
        "market_cap": "$4,158,118,637",
        "volume_24h": "$252,393,600",
        "trend_24h": "up",
        "trend_7d": "up",
        "change_class": "positive"
      },
      {
        "rank": "0",
        "name": "aixbt",
        "symbol": "AIXBT",
        "logo": "",
        "price": "$0.130331",
        "change_1h": "+0.09%",
        "change_24h": "+3.65%",
        "change_7d": "-2.90%",
        "market_cap": "$123,263,659",
        "volume_24h": "$60,523,623",
        "trend_24h": "up",
        "trend_7d": "down",
        "change_class": "positive"
      }
    ],
    "top_losers_24h": [
      {
        "rank": "0",
        "name": "Hifi Finance",
        "symbol": "HIFI",
        "logo": "",
        "price": "$0.084079",
        "change_1h": "-3.18%",
        "change_24h": "-35.59%",
        "change_7d": "-34.15%",
        "market_cap": "$11,923,824",
        "volume_24h": "$60,421,613",
        "trend_24h": "down",
        "trend_7d": "down",
        "change_class": "negative"
      },
      {
        "rank": "0",
        "name": "Bubblemaps",
        "symbol": "BMT",
        "logo": "",
        "price": "$0.087909",
        "change_1h": "+1.65%",
        "change_24h": "-34.69%",
        "change_7d": "-36.36%",
        "market_cap": "$31,636,470",
        "volume_24h": "$157,699,116",
        "trend_24h": "down",
        "trend_7d": "down",
        "change_class": "negative"
      },
      {
        "rank": "0",
        "name": "Humanity Protocol",
        "symbol": "H",
        "logo": "",
        "price": "$0.081386",
        "change_1h": "+4.53%",
        "change_24h": "-20.18%",
        "change_7d": "+282.73%",
        "market_cap": "$148,529,706",
        "volume_24h": "$252,089,744",
        "trend_24h": "down",
        "trend_7d": "up",
        "change_class": "negative"
      },
      {
        "rank": "0",
        "name": "EGL1",
        "symbol": "EGL1",
        "logo": "",
        "price": "$0.068648",
        "change_1h": "-3.43%",
        "change_24h": "-14.43%",
        "change_7d": "-0.35%",
        "market_cap": "$68,648,476",
        "volume_24h": "$121,032,138",
        "trend_24h": "down",
        "trend_7d": "down",
        "change_class": "negative"
      },
      {
        "rank": "0",
        "name": "Wayfinder",
        "symbol": "PROMPT",
        "logo": "",
        "price": "$0.119313",
        "change_1h": "+0.19%",
        "change_24h": "-8.96%",
        "change_7d": "-12.53%",
        "market_cap": "$0",
        "volume_24h": "$51,689,877",
        "trend_24h": "down",
        "trend_7d": "down",
        "change_class": "negative"
      },
      {
        "rank": "0",
        "name": "Roam",
        "symbol": "ROAM",
        "logo": "",
        "price": "$0.124120",
        "change_1h": "+0.31%",
        "change_24h": "-8.84%",
        "change_7d": "-11.73%",
        "market_cap": "$37,468,799",
        "volume_24h": "$77,727,759",
        "trend_24h": "down",
        "trend_7d": "down",
        "change_class": "negative"
      },
      {
        "rank": "0",
        "name": "Impossible Cloud Network",
        "symbol": "ICNT",
        "logo": "",
        "price": "$0.244057",
        "change_1h": "+3.15%",
        "change_24h": "-6.05%",
        "change_7d": "-59.88%",
        "market_cap": "$40,812,662",
        "volume_24h": "$52,102,096",
        "trend_24h": "down",
        "trend_7d": "down",
        "change_class": "negative"
      },
      {
        "rank": "0",
        "name": "Strike",
        "symbol": "STRK",
        "logo": "",
        "price": "$7.85",
        "change_1h": "+2.89%",
        "change_24h": "-5.05%",
        "change_7d": "+36.47%",
        "market_cap": "$44,013,838",
        "volume_24h": "$69,830,065",
        "trend_24h": "down",
        "trend_7d": "up",
        "change_class": "negative"
      },
      {
        "rank": "0",
        "name": "Bulla",
        "symbol": "BULLA",
        "logo": "",
        "price": "$0.072511",
        "change_1h": "+0.51%",
        "change_24h": "-4.91%",
        "change_7d": "-34.06%",
        "market_cap": "$20,303,172",
        "volume_24h": "$84,573,343",
        "trend_24h": "down",
        "trend_7d": "down",
        "change_class": "negative"
      },
      {
        "rank": "0",
        "name": "Pudgy Penguins",
        "symbol": "PENGU",
        "logo": "",
        "price": "$0.015663",
        "change_1h": "+1.02%",
        "change_24h": "-3.89%",
        "change_7d": "+8.93%",
        "market_cap": "$984,606,364",
        "volume_24h": "$296,392,558",
        "trend_24h": "down",
        "trend_7d": "up",
        "change_class": "negative"
      }
    ],
    "top_gainers_7d": [
      {
        "rank": "0",
        "name": "Humanity Protocol",
        "symbol": "H",
        "logo": "",
        "price": "$0.081386",
        "change_1h": "+4.53%",
        "change_24h": "-20.18%",
        "change_7d": "+282.73%",
        "market_cap": "$148,529,706",
        "volume_24h": "$252,089,744",
        "trend_24h": "down",
        "trend_7d": "up",
        "change_class": "positive"
      },
      {
        "rank": "0",
        "name": "Bedrock",
        "symbol": "BR",
        "logo": "",
        "price": "$0.128044",
        "change_1h": "+0.01%",
        "change_24h": "+0.02%",
        "change_7d": "+60.80%",
        "market_cap": "$26,889,321",
        "volume_24h": "$4,276,208,950",
        "trend_24h": "up",
        "trend_7d": "up",
        "change_class": "positive"
      },
      {
        "rank": "0",
        "name": "GUNZ",
        "symbol": "GUN",
        "logo": "",
        "price": "$0.035852",
        "change_1h": "-0.67%",
        "change_24h": "+12.52%",
        "change_7d": "+55.29%",
        "market_cap": "$34,220,853",
        "volume_24h": "$75,262,777",
        "trend_24h": "up",
        "trend_7d": "up",
        "change_class": "positive"
      },
      {
        "rank": "0",
        "name": "Strike",
        "symbol": "STRK",
        "logo": "",
        "price": "$7.85",
        "change_1h": "+2.89%",
        "change_24h": "-5.05%",
        "change_7d": "+36.47%",
        "market_cap": "$44,013,838",
        "volume_24h": "$69,830,065",
        "trend_24h": "down",
        "trend_7d": "up",
        "change_class": "positive"
      },
      {
        "rank": "0",
        "name": "FUNToken",
        "symbol": "FUN",
        "logo": "",
        "price": "$0.013453",
        "change_1h": "+0.67%",
        "change_24h": "-0.87%",
        "change_7d": "+34.76%",
        "market_cap": "$145,538,396",
        "volume_24h": "$76,362,063",
        "trend_24h": "down",
        "trend_7d": "up",
        "change_class": "positive"
      },
      {
        "rank": "0",
        "name": "Bonk",
        "symbol": "BONK",
        "logo": "",
        "price": "$0.000018",
        "change_1h": "+0.85%",
        "change_24h": "+8.98%",
        "change_7d": "+25.46%",
        "market_cap": "$1,476,161,183",
        "volume_24h": "$644,323,594",
        "trend_24h": "up",
        "trend_7d": "up",
        "change_class": "positive"
      },
      {
        "rank": "0",
        "name": "CARV",
        "symbol": "CARV",
        "logo": "",
        "price": "$0.295334",
        "change_1h": "-1.38%",
        "change_24h": "+14.40%",
        "change_7d": "+24.93%",
        "market_cap": "$86,661,519",
        "volume_24h": "$341,769,740",
        "trend_24h": "up",
        "trend_7d": "up",
        "change_class": "positive"
      },
      {
        "rank": "0",
        "name": "Moo Deng (moodengsol.com)",
        "symbol": "MOODENG",
        "logo": "",
        "price": "$0.183888",
        "change_1h": "+1.55%",
        "change_24h": "+4.95%",
        "change_7d": "+24.08%",
        "market_cap": "$182,043,909",
        "volume_24h": "$158,454,763",
        "trend_24h": "up",
        "trend_7d": "up",
        "change_class": "positive"
      },
      {
        "rank": "0",
        "name": "Stratis [New]",
        "symbol": "STRAX",
        "logo": "",
        "price": "$0.050098",
        "change_1h": "-0.17%",
        "change_24h": "+4.41%",
        "change_7d": "+15.99%",
        "market_cap": "$99,280,560",
        "volume_24h": "$58,398,332",
        "trend_24h": "up",
        "trend_7d": "up",
        "change_class": "positive"
      },
      {
        "rank": "0",
        "name": "Neiro (First Neiro On Ethereum)",
        "symbol": "NEIRO",
        "logo": "",
        "price": "$0.000419",
        "change_1h": "+0.53%",
        "change_24h": "-3.27%",
        "change_7d": "+12.44%",
        "market_cap": "$176,088,139",
        "volume_24h": "$80,263,496",
        "trend_24h": "down",
        "trend_7d": "up",
        "change_class": "positive"
      }
    ],
    "top_losers_7d": [
      {
        "rank": "0",
        "name": "StormX",
        "symbol": "STMX",
        "logo": "",
        "price": "$0.000117",
        "change_1h": "+2.39%",
        "change_24h": "+26.10%",
        "change_7d": "-91.36%",
        "market_cap": "$1,451,053",
        "volume_24h": "$366,522,156",
        "trend_24h": "up",
        "trend_7d": "down",
        "change_class": "negative"
      },
      {
        "rank": "0",
        "name": "Impossible Cloud Network",
        "symbol": "ICNT",
        "logo": "",
        "price": "$0.244057",
        "change_1h": "+3.15%",
        "change_24h": "-6.05%",
        "change_7d": "-59.88%",
        "market_cap": "$40,812,662",
        "volume_24h": "$52,102,096",
        "trend_24h": "down",
        "trend_7d": "down",
        "change_class": "negative"
      },
      {
        "rank": "0",
        "name": "Bubblemaps",
        "symbol": "BMT",
        "logo": "",
        "price": "$0.087909",
        "change_1h": "+1.65%",
        "change_24h": "-34.69%",
        "change_7d": "-36.36%",
        "market_cap": "$31,636,470",
        "volume_24h": "$157,699,116",
        "trend_24h": "down",
        "trend_7d": "down",
        "change_class": "negative"
      },
      {
        "rank": "0",
        "name": "Hifi Finance",
        "symbol": "HIFI",
        "logo": "",
        "price": "$0.084079",
        "change_1h": "-3.18%",
        "change_24h": "-35.59%",
        "change_7d": "-34.15%",
        "market_cap": "$11,923,824",
        "volume_24h": "$60,421,613",
        "trend_24h": "down",
        "trend_7d": "down",
        "change_class": "negative"
      },
      {
        "rank": "0",
        "name": "Bulla",
        "symbol": "BULLA",
        "logo": "",
        "price": "$0.072511",
        "change_1h": "+0.51%",
        "change_24h": "-4.91%",
        "change_7d": "-34.06%",
        "market_cap": "$20,303,172",
        "volume_24h": "$84,573,343",
        "trend_24h": "down",
        "trend_7d": "down",
        "change_class": "negative"
      },
      {
        "rank": "0",
        "name": "Bitcoin SV",
        "symbol": "BSV",
        "logo": "",
        "price": "$24.10",
        "change_1h": "+0.27%",
        "change_24h": "+2.68%",
        "change_7d": "-21.71%",
        "market_cap": "$479,232,754",
        "volume_24h": "$67,442,355",
        "trend_24h": "up",
        "trend_7d": "down",
        "change_class": "negative"
      },
      {
        "rank": "0",
        "name": "Newton Protocol",
        "symbol": "NEWT",
        "logo": "",
        "price": "$0.326313",
        "change_1h": "-0.30%",
        "change_24h": "-2.97%",
        "change_7d": "-16.39%",
        "market_cap": "$70,157,288",
        "volume_24h": "$206,678,003",
        "trend_24h": "down",
        "trend_7d": "down",
        "change_class": "negative"
      },
      {
        "rank": "0",
        "name": "Wayfinder",
        "symbol": "PROMPT",
        "logo": "",
        "price": "$0.119313",
        "change_1h": "+0.19%",
        "change_24h": "-8.96%",
        "change_7d": "-12.53%",
        "market_cap": "$0",
        "volume_24h": "$51,689,877",
        "trend_24h": "down",
        "trend_7d": "down",
        "change_class": "negative"
      },
      {
        "rank": "0",
        "name": "Roam",
        "symbol": "ROAM",
        "logo": "",
        "price": "$0.124120",
        "change_1h": "+0.31%",
        "change_24h": "-8.84%",
        "change_7d": "-11.73%",
        "market_cap": "$37,468,799",
        "volume_24h": "$77,727,759",
        "trend_24h": "down",
        "trend_7d": "down",
        "change_class": "negative"
      },
      {
        "rank": "0",
        "name": "Aptos",
        "symbol": "APT",
        "logo": "",
        "price": "$4.41",
        "change_1h": "-0.20%",
        "change_24h": "+0.18%",
        "change_7d": "-8.56%",
        "market_cap": "$2,845,651,372",
        "volume_24h": "$71,817,994",
        "trend_24h": "up",
        "trend_7d": "down",
        "change_class": "negative"
      }
    ]
  },
  "most_visited": [
    {
      "rank": "0",
      "name": "Bitcoin",
      "symbol": "BTC",
      "logo": "",
      "price": "$108111.28",
      "change_1h": "-0.05%",
      "change_24h": "+0.10%",
      "change_7d": "+0.70%",
      "market_cap": "$2,150,126,591,885",
      "volume_24h": "$31,039,354,439",
      "trend_24h": "up",
      "trend_7d": "up"
    },
    {
      "rank": "0",
      "name": "Ethereum",
      "symbol": "ETH",
      "logo": "",
      "price": "$2515.29",
      "change_1h": "+0.26%",
      "change_24h": "+0.61%",
      "change_7d": "+3.21%",
      "market_cap": "$303,638,709,642",
      "volume_24h": "$9,691,100,268",
      "trend_24h": "up",
      "trend_7d": "up"
    },
    {
      "rank": "0",
      "name": "Tether USDt",
      "symbol": "USDT",
      "logo": "",
      "price": "$1.00",
      "change_1h": "-0.01%",
      "change_24h": "+0.01%",
      "change_7d": "+0.01%",
      "market_cap": "$158,647,590,545",
      "volume_24h": "$37,983,991,108",
      "trend_24h": "up",
      "trend_7d": "up"
    },
    {
      "rank": "0",
      "name": "XRP",
      "symbol": "XRP",
      "logo": "",
      "price": "$2.22",
      "change_1h": "+0.22%",
      "change_24h": "-0.11%",
      "change_7d": "+1.30%",
      "market_cap": "$130,889,694,239",
      "volume_24h": "$1,216,572,632",
      "trend_24h": "down",
      "trend_7d": "up"
    },
    {
      "rank": "0",
      "name": "BNB",
      "symbol": "BNB",
      "logo": "",
      "price": "$655.64",
      "change_1h": "+0.09%",
      "change_24h": "+0.39%",
      "change_7d": "+1.07%",
      "market_cap": "$92,370,429,506",
      "volume_24h": "$1,201,619,961",
      "trend_24h": "up",
      "trend_7d": "up"
    },
    {
      "rank": "0",
      "name": "Solana",
      "symbol": "SOL",
      "logo": "",
      "price": "$147.35",
      "change_1h": "+0.12%",
      "change_24h": "+0.12%",
      "change_7d": "-2.39%",
      "market_cap": "$78,811,736,058",
      "volume_24h": "$1,681,572,040",
      "trend_24h": "up",
      "trend_7d": "down"
    },
    {
      "rank": "0",
      "name": "USDC",
      "symbol": "USDC",
      "logo": "",
      "price": "$0.999936",
      "change_1h": "-0.00%",
      "change_24h": "-0.00%",
      "change_7d": "+0.01%",
      "market_cap": "$62,162,725,135",
      "volume_24h": "$3,763,323,550",
      "trend_24h": "down",
      "trend_7d": "up"
    },
    {
      "rank": "0",
      "name": "TRON",
      "symbol": "TRX",
      "logo": "",
      "price": "$0.283298",
      "change_1h": "-0.23%",
      "change_24h": "-0.10%",
      "change_7d": "+3.17%",
      "market_cap": "$26,851,703,244",
      "volume_24h": "$293,959,691",
      "trend_24h": "down",
      "trend_7d": "up"
    },
    {
      "rank": "0",
      "name": "Dogecoin",
      "symbol": "DOGE",
      "logo": "",
      "price": "$0.164275",
      "change_1h": "+0.02%",
      "change_24h": "+0.87%",
      "change_7d": "-0.01%",
      "market_cap": "$24,637,097,141",
      "volume_24h": "$485,996,297",
      "trend_24h": "up",
      "trend_7d": "down"
    },
    {
      "rank": "0",
      "name": "Cardano",
      "symbol": "ADA",
      "logo": "",
      "price": "$0.574893",
      "change_1h": "+0.02%",
      "change_24h": "+0.51%",
      "change_7d": "+1.60%",
      "market_cap": "$20,342,029,528",
      "volume_24h": "$324,312,265",
      "trend_24h": "up",
      "trend_7d": "up"
    }
  ],
  "all_coins": [
    {
      "rank": "0",
      "name": "Bitcoin",
      "symbol": "BTC",
      "logo": "",
      "price": "$108111.28",
      "change_1h": "-0.05%",
      "change_24h": "+0.10%",
      "change_7d": "+0.70%",
      "market_cap": "$2,150,126,591,885",
      "volume_24h": "$31,039,354,439",
      "trend_24h": "up",
      "trend_7d": "up"
    },
    {
      "rank": "0",
      "name": "Ethereum",
      "symbol": "ETH",
      "logo": "",
      "price": "$2515.29",
      "change_1h": "+0.26%",
      "change_24h": "+0.61%",
      "change_7d": "+3.21%",
      "market_cap": "$303,638,709,642",
      "volume_24h": "$9,691,100,268",
      "trend_24h": "up",
      "trend_7d": "up"
    },
    {
      "rank": "0",
      "name": "Tether USDt",
      "symbol": "USDT",
      "logo": "",
      "price": "$1.00",
      "change_1h": "-0.01%",
      "change_24h": "+0.01%",
      "change_7d": "+0.01%",
      "market_cap": "$158,647,590,545",
      "volume_24h": "$37,983,991,108",
      "trend_24h": "up",
      "trend_7d": "up"
    },
    {
      "rank": "0",
      "name": "XRP",
      "symbol": "XRP",
      "logo": "",
      "price": "$2.22",
      "change_1h": "+0.22%",
      "change_24h": "-0.11%",
      "change_7d": "+1.30%",
      "market_cap": "$130,889,694,239",
      "volume_24h": "$1,216,572,632",
      "trend_24h": "down",
      "trend_7d": "up"
    },
    {
      "rank": "0",
      "name": "BNB",
      "symbol": "BNB",
      "logo": "",
      "price": "$655.64",
      "change_1h": "+0.09%",
      "change_24h": "+0.39%",
      "change_7d": "+1.07%",
      "market_cap": "$92,370,429,506",
      "volume_24h": "$1,201,619,961",
      "trend_24h": "up",
      "trend_7d": "up"
    },
    {
      "rank": "0",
      "name": "Solana",
      "symbol": "SOL",
      "logo": "",
      "price": "$147.35",
      "change_1h": "+0.12%",
      "change_24h": "+0.12%",
      "change_7d": "-2.39%",
      "market_cap": "$78,811,736,058",
      "volume_24h": "$1,681,572,040",
      "trend_24h": "up",
      "trend_7d": "down"
    },
    {
      "rank": "0",
      "name": "USDC",
      "symbol": "USDC",
      "logo": "",
      "price": "$0.999936",
      "change_1h": "-0.00%",
      "change_24h": "-0.00%",
      "change_7d": "+0.01%",
      "market_cap": "$62,162,725,135",
      "volume_24h": "$3,763,323,550",
      "trend_24h": "down",
      "trend_7d": "up"
    },
    {
      "rank": "0",
      "name": "TRON",
      "symbol": "TRX",
      "logo": "",
      "price": "$0.283298",
      "change_1h": "-0.23%",
      "change_24h": "-0.10%",
      "change_7d": "+3.17%",
      "market_cap": "$26,851,703,244",
      "volume_24h": "$293,959,691",
      "trend_24h": "down",
      "trend_7d": "up"
    },
    {
      "rank": "0",
      "name": "Dogecoin",
      "symbol": "DOGE",
      "logo": "",
      "price": "$0.164275",
      "change_1h": "+0.02%",
      "change_24h": "+0.87%",
      "change_7d": "-0.01%",
      "market_cap": "$24,637,097,141",
      "volume_24h": "$485,996,297",
      "trend_24h": "up",
      "trend_7d": "down"
    },
    {
      "rank": "0",
      "name": "Cardano",
      "symbol": "ADA",
      "logo": "",
      "price": "$0.574893",
      "change_1h": "+0.02%",
      "change_24h": "+0.51%",
      "change_7d": "+1.60%",
      "market_cap": "$20,342,029,528",
      "volume_24h": "$324,312,265",
      "trend_24h": "up",
      "trend_7d": "up"
    },
    {
      "rank": "0",
      "name": "Hyperliquid",
      "symbol": "HYPE",
      "logo": "",
      "price": "$39.01",
      "change_1h": "+0.39%",
      "change_24h": "+0.85%",
      "change_7d": "+3.32%",
      "market_cap": "$13,025,975,623",
      "volume_24h": "$153,250,313",
      "trend_24h": "up",
      "trend_7d": "up"
    },
    {
      "rank": "0",
      "name": "Sui",
      "symbol": "SUI",
      "logo": "",
      "price": "$2.90",
      "change_1h": "+0.05%",
      "change_24h": "+0.79%",
      "change_7d": "+3.48%",
      "market_cap": "$10,008,151,189",
      "volume_24h": "$473,159,571",
      "trend_24h": "up",
      "trend_7d": "up"
    },
    {
      "rank": "0",
      "name": "Bitcoin Cash",
      "symbol": "BCH",
      "logo": "",
      "price": "$486.96",
      "change_1h": "+0.29%",
      "change_24h": "+0.23%",
      "change_7d": "-0.87%",
      "market_cap": "$9,687,183,546",
      "volume_24h": "$260,368,337",
      "trend_24h": "up",
      "trend_7d": "down"
    },
    {
      "rank": "0",
      "name": "Chainlink",
      "symbol": "LINK",
      "logo": "",
      "price": "$13.19",
      "change_1h": "+0.05%",
      "change_24h": "+0.61%",
      "change_7d": "-1.52%",
      "market_cap": "$8,945,632,828",
      "volume_24h": "$157,646,825",
      "trend_24h": "up",
      "trend_7d": "down"
    },
    {
      "rank": "0",
      "name": "Avalanche",
      "symbol": "AVAX",
      "logo": "",
      "price": "$17.87",
      "change_1h": "-0.12%",
      "change_24h": "+0.62%",
      "change_7d": "-0.56%",
      "market_cap": "$7,546,670,261",
      "volume_24h": "$118,782,320",
      "trend_24h": "up",
      "trend_7d": "down"
    },
    {
      "rank": "0",
      "name": "Stellar",
      "symbol": "XLM",
      "logo": "",
      "price": "$0.237411",
      "change_1h": "+0.30%",
      "change_24h": "-0.32%",
      "change_7d": "-0.86%",
      "market_cap": "$7,344,413,681",
      "volume_24h": "$61,400,946",
      "trend_24h": "down",
      "trend_7d": "down"
    },
    {
      "rank": "0",
      "name": "Toncoin",
      "symbol": "TON",
      "logo": "",
      "price": "$2.76",
      "change_1h": "+0.27%",
      "change_24h": "+0.04%",
      "change_7d": "-3.51%",
      "market_cap": "$6,800,831,694",
      "volume_24h": "$84,930,997",
      "trend_24h": "up",
      "trend_7d": "down"
    },
    {
      "rank": "0",
      "name": "Shiba Inu",
      "symbol": "SHIB",
      "logo": "",
      "price": "$0.000011",
      "change_1h": "+0.03%",
      "change_24h": "+0.51%",
      "change_7d": "-0.94%",
      "market_cap": "$6,747,221,725",
      "volume_24h": "$74,234,401",
      "trend_24h": "up",
      "trend_7d": "down"
    },
    {
      "rank": "0",
      "name": "Litecoin",
      "symbol": "LTC",
      "logo": "",
      "price": "$87.32",
      "change_1h": "-0.22%",
      "change_24h": "+0.92%",
      "change_7d": "+1.24%",
      "market_cap": "$6,639,952,499",
      "volume_24h": "$249,727,325",
      "trend_24h": "up",
      "trend_7d": "up"
    },
    {
      "rank": "0",
      "name": "Hedera",
      "symbol": "HBAR",
      "logo": "",
      "price": "$0.154681",
      "change_1h": "-0.07%",
      "change_24h": "+0.89%",
      "change_7d": "+4.21%",
      "market_cap": "$6,557,129,200",
      "volume_24h": "$125,587,030",
      "trend_24h": "up",
      "trend_7d": "up"
    },
    {
      "rank": "0",
      "name": "Monero",
      "symbol": "XMR",
      "logo": "",
      "price": "$314.58",
      "change_1h": "-0.06%",
      "change_24h": "+0.24%",
      "change_7d": "+2.33%",
      "market_cap": "$5,803,028,429",
      "volume_24h": "$57,215,348",
      "trend_24h": "up",
      "trend_7d": "up"
    },
    {
      "rank": "0",
      "name": "Dai",
      "symbol": "DAI",
      "logo": "",
      "price": "$0.999923",
      "change_1h": "-0.01%",
      "change_24h": "-0.01%",
      "change_7d": "+0.01%",
      "market_cap": "$5,364,967,261",
      "volume_24h": "$18,429,079,784",
      "trend_24h": "down",
      "trend_7d": "up"
    },
    {
      "rank": "0",
      "name": "Polkadot",
      "symbol": "DOT",
      "logo": "",
      "price": "$3.35",
      "change_1h": "-0.01%",
      "change_24h": "-0.20%",
      "change_7d": "-1.88%",
      "market_cap": "$5,339,295,996",
      "volume_24h": "$107,143,460",
      "trend_24h": "down",
      "trend_7d": "down"
    },
    {
      "rank": "0",
      "name": "Ethena USDe",
      "symbol": "USDe",
      "logo": "",
      "price": "$1.00",
      "change_1h": "-0.01%",
      "change_24h": "+0.02%",
      "change_7d": "+0.02%",
      "market_cap": "$5,308,048,249",
      "volume_24h": "$69,333,958",
      "trend_24h": "up",
      "trend_7d": "up"
    },
    {
      "rank": "0",
      "name": "Uniswap",
      "symbol": "UNI",
      "logo": "",
      "price": "$7.02",
      "change_1h": "-0.25%",
      "change_24h": "+1.61%",
      "change_7d": "-1.66%",
      "market_cap": "$4,415,055,723",
      "volume_24h": "$239,227,878",
      "trend_24h": "up",
      "trend_7d": "down"
    },
    {
      "rank": "0",
      "name": "Aave",
      "symbol": "AAVE",
      "logo": "",
      "price": "$274.00",
      "change_1h": "+0.32%",
      "change_24h": "+3.80%",
      "change_7d": "+5.83%",
      "market_cap": "$4,158,118,637",
      "volume_24h": "$252,393,600",
      "trend_24h": "up",
      "trend_7d": "up"
    },
    {
      "rank": "0",
      "name": "Pepe",
      "symbol": "PEPE",
      "logo": "",
      "price": "$0.000010",
      "change_1h": "+0.04%",
      "change_24h": "+0.84%",
      "change_7d": "+1.39%",
      "market_cap": "$4,071,533,443",
      "volume_24h": "$427,949,094",
      "trend_24h": "up",
      "trend_7d": "up"
    },
    {
      "rank": "0",
      "name": "Bittensor",
      "symbol": "TAO",
      "logo": "",
      "price": "$321.95",
      "change_1h": "+0.47%",
      "change_24h": "-0.70%",
      "change_7d": "-2.92%",
      "market_cap": "$2,886,878,517",
      "volume_24h": "$63,476,308",
      "trend_24h": "down",
      "trend_7d": "down"
    },
    {
      "rank": "0",
      "name": "Aptos",
      "symbol": "APT",
      "logo": "",
      "price": "$4.41",
      "change_1h": "-0.20%",
      "change_24h": "+0.18%",
      "change_7d": "-8.56%",
      "market_cap": "$2,845,651,372",
      "volume_24h": "$71,817,994",
      "trend_24h": "up",
      "trend_7d": "down"
    },
    {
      "rank": "0",
      "name": "NEAR Protocol",
      "symbol": "NEAR",
      "logo": "",
      "price": "$2.14",
      "change_1h": "+0.09%",
      "change_24h": "+0.82%",
      "change_7d": "-1.10%",
      "market_cap": "$2,634,907,313",
      "volume_24h": "$83,204,038",
      "trend_24h": "up",
      "trend_7d": "down"
    },
    {
      "rank": "0",
      "name": "Ondo",
      "symbol": "ONDO",
      "logo": "",
      "price": "$0.781324",
      "change_1h": "+0.36%",
      "change_24h": "+0.75%",
      "change_7d": "+2.57%",
      "market_cap": "$2,468,285,846",
      "volume_24h": "$62,966,316",
      "trend_24h": "up",
      "trend_7d": "up"
    },
    {
      "rank": "0",
      "name": "World Liberty Financial USD",
      "symbol": "USD1",
      "logo": "",
      "price": "$1.00",
      "change_1h": "-0.00%",
      "change_24h": "-0.00%",
      "change_7d": "+0.03%",
      "market_cap": "$2,204,303,289",
      "volume_24h": "$668,910,440",
      "trend_24h": "down",
      "trend_7d": "up"
    },
    {
      "rank": "0",
      "name": "POL (prev. MATIC)",
      "symbol": "POL",
      "logo": "",
      "price": "$0.182639",
      "change_1h": "-0.11%",
      "change_24h": "+2.04%",
      "change_7d": "+2.64%",
      "market_cap": "$1,910,205,490",
      "volume_24h": "$87,843,690",
      "trend_24h": "up",
      "trend_7d": "up"
    },
    {
      "rank": "0",
      "name": "Mantle",
      "symbol": "MNT",
      "logo": "",
      "price": "$0.563601",
      "change_1h": "+0.00%",
      "change_24h": "+0.05%",
      "change_7d": "-7.25%",
      "market_cap": "$1,896,964,019",
      "volume_24h": "$173,459,326",
      "trend_24h": "up",
      "trend_7d": "down"
    },
    {
      "rank": "0",
      "name": "OFFICIAL TRUMP",
      "symbol": "TRUMP",
      "logo": "",
      "price": "$8.54",
      "change_1h": "-0.01%",
      "change_24h": "+0.21%",
      "change_7d": "-6.23%",
      "market_cap": "$1,707,193,132",
      "volume_24h": "$110,520,496",
      "trend_24h": "up",
      "trend_7d": "down"
    },
    {
      "rank": "0",
      "name": "Arbitrum",
      "symbol": "ARB",
      "logo": "",
      "price": "$0.326559",
      "change_1h": "+0.58%",
      "change_24h": "+1.58%",
      "change_7d": "+5.45%",
      "market_cap": "$1,620,788,322",
      "volume_24h": "$125,562,197",
      "trend_24h": "up",
      "trend_7d": "up"
    },
    {
      "rank": "0",
      "name": "Ethena",
      "symbol": "ENA",
      "logo": "",
      "price": "$0.254562",
      "change_1h": "+0.14%",
      "change_24h": "+0.76%",
      "change_7d": "-3.96%",
      "market_cap": "$1,617,659,362",
      "volume_24h": "$74,587,093",
      "trend_24h": "up",
      "trend_7d": "down"
    },
    {
      "rank": "0",
      "name": "Artificial Superintelligence Alliance",
      "symbol": "FET",
      "logo": "",
      "price": "$0.660987",
      "change_1h": "-0.27%",
      "change_24h": "-2.23%",
      "change_7d": "-3.66%",
      "market_cap": "$1,581,490,026",
      "volume_24h": "$71,995,479",
      "trend_24h": "down",
      "trend_7d": "down"
    },
    {
      "rank": "0",
      "name": "Cosmos",
      "symbol": "ATOM",
      "logo": "",
      "price": "$4.00",
      "change_1h": "+0.15%",
      "change_24h": "+0.16%",
      "change_7d": "+0.17%",
      "market_cap": "$1,565,475,808",
      "volume_24h": "$54,585,397",
      "trend_24h": "up",
      "trend_7d": "up"
    },
    {
      "rank": "0",
      "name": "Filecoin",
      "symbol": "FIL",
      "logo": "",
      "price": "$2.25",
      "change_1h": "+0.10%",
      "change_24h": "-0.06%",
      "change_7d": "-1.09%",
      "market_cap": "$1,530,520,454",
      "volume_24h": "$111,493,337",
      "trend_24h": "down",
      "trend_7d": "down"
    },
    {
      "rank": "0",
      "name": "Bonk",
      "symbol": "BONK",
      "logo": "",
      "price": "$0.000018",
      "change_1h": "+0.85%",
      "change_24h": "+8.98%",
      "change_7d": "+25.46%",
      "market_cap": "$1,476,161,183",
      "volume_24h": "$644,323,594",
      "trend_24h": "up",
      "trend_7d": "up"
    },
    {
      "rank": "0",
      "name": "First Digital USD",
      "symbol": "FDUSD",
      "logo": "",
      "price": "$0.998058",
      "change_1h": "-0.02%",
      "change_24h": "-0.02%",
      "change_7d": "-0.02%",
      "market_cap": "$1,469,592,503",
      "volume_24h": "$2,161,358,978",
      "trend_24h": "down",
      "trend_7d": "down"
    },
    {
      "rank": "0",
      "name": "Worldcoin",
      "symbol": "WLD",
      "logo": "",
      "price": "$0.865555",
      "change_1h": "-0.20%",
      "change_24h": "-0.80%",
      "change_7d": "-3.35%",
      "market_cap": "$1,465,280,690",
      "volume_24h": "$85,492,605",
      "trend_24h": "down",
      "trend_7d": "down"
    },
    {
      "rank": "0",
      "name": "Sei",
      "symbol": "SEI",
      "logo": "",
      "price": "$0.262208",
      "change_1h": "-0.80%",
      "change_24h": "+0.83%",
      "change_7d": "-8.09%",
      "market_cap": "$1,457,075,021",
      "volume_24h": "$107,230,806",
      "trend_24h": "up",
      "trend_7d": "down"
    },
    {
      "rank": "0",
      "name": "Fartcoin",
      "symbol": "FARTCOIN",
      "logo": "",
      "price": "$1.18",
      "change_1h": "-0.09%",
      "change_24h": "+0.79%",
      "change_7d": "+8.71%",
      "market_cap": "$1,177,430,340",
      "volume_24h": "$86,365,694",
      "trend_24h": "up",
      "trend_7d": "up"
    },
    {
      "rank": "0",
      "name": "Injective",
      "symbol": "INJ",
      "logo": "",
      "price": "$10.57",
      "change_1h": "+0.14%",
      "change_24h": "-2.49%",
      "change_7d": "-3.44%",
      "market_cap": "$1,056,864,629",
      "volume_24h": "$67,598,646",
      "trend_24h": "down",
      "trend_7d": "down"
    },
    {
      "rank": "0",
      "name": "Celestia",
      "symbol": "TIA",
      "logo": "",
      "price": "$1.48",
      "change_1h": "+0.24%",
      "change_24h": "-2.31%",
      "change_7d": "+0.21%",
      "market_cap": "$1,035,606,632",
      "volume_24h": "$88,783,619",
      "trend_24h": "down",
      "trend_7d": "up"
    },
    {
      "rank": "0",
      "name": "Virtuals Protocol",
      "symbol": "VIRTUAL",
      "logo": "",
      "price": "$1.54",
      "change_1h": "+0.26%",
      "change_24h": "-0.69%",
      "change_7d": "+0.57%",
      "market_cap": "$1,006,900,155",
      "volume_24h": "$137,803,515",
      "trend_24h": "down",
      "trend_7d": "up"
    },
    {
      "rank": "0",
      "name": "Pudgy Penguins",
      "symbol": "PENGU",
      "logo": "",
      "price": "$0.015663",
      "change_1h": "+1.02%",
      "change_24h": "-3.89%",
      "change_7d": "+8.93%",
      "market_cap": "$984,606,364",
      "volume_24h": "$296,392,558",
      "trend_24h": "down",
      "trend_7d": "up"
    },
    {
      "rank": "0",
      "name": "Optimism",
      "symbol": "OP",
      "logo": "",
      "price": "$0.529445",
      "change_1h": "+0.37%",
      "change_24h": "-0.36%",
      "change_7d": "-3.99%",
      "market_cap": "$927,687,012",
      "volume_24h": "$82,379,810",
      "trend_24h": "down",
      "trend_7d": "down"
    },
    {
      "rank": "0",
      "name": "dogwifhat",
      "symbol": "WIF",
      "logo": "",
      "price": "$0.835905",
      "change_1h": "+0.12%",
      "change_24h": "+0.08%",
      "change_7d": "-0.14%",
      "market_cap": "$834,935,963",
      "volume_24h": "$274,032,469",
      "trend_24h": "up",
      "trend_7d": "down"
    },
    {
      "rank": "0",
      "name": "Curve DAO Token",
      "symbol": "CRV",
      "logo": "",
      "price": "$0.497556",
      "change_1h": "-0.05%",
      "change_24h": "-0.51%",
      "change_7d": "-3.11%",
      "market_cap": "$677,223,116",
      "volume_24h": "$56,676,990",
      "trend_24h": "down",
      "trend_7d": "down"
    },
    {
      "rank": "0",
      "name": "Maple Finance",
      "symbol": "SYRUP",
      "logo": "",
      "price": "$0.550541",
      "change_1h": "+0.07%",
      "change_24h": "+3.40%",
      "change_7d": "-8.09%",
      "market_cap": "$654,919,360",
      "volume_24h": "$68,460,467",
      "trend_24h": "up",
      "trend_7d": "down"
    },
    {
      "rank": "0",
      "name": "Zcash",
      "symbol": "ZEC",
      "logo": "",
      "price": "$39.10",
      "change_1h": "+0.08%",
      "change_24h": "-2.74%",
      "change_7d": "+0.39%",
      "market_cap": "$654,343,016",
      "volume_24h": "$86,234,570",
      "trend_24h": "down",
      "trend_7d": "up"
    },
    {
      "rank": "0",
      "name": "Gala",
      "symbol": "GALA",
      "logo": "",
      "price": "$0.013889",
      "change_1h": "+0.45%",
      "change_24h": "+0.39%",
      "change_7d": "-0.61%",
      "market_cap": "$627,107,681",
      "volume_24h": "$55,154,915",
      "trend_24h": "up",
      "trend_7d": "down"
    },
    {
      "rank": "0",
      "name": "AB",
      "symbol": "AB",
      "logo": "",
      "price": "$0.008126",
      "change_1h": "+0.08%",
      "change_24h": "+1.33%",
      "change_7d": "-1.86%",
      "market_cap": "$538,557,157",
      "volume_24h": "$55,529,820",
      "trend_24h": "up",
      "trend_7d": "down"
    },
    {
      "rank": "0",
      "name": "Bitcoin SV",
      "symbol": "BSV",
      "logo": "",
      "price": "$24.10",
      "change_1h": "+0.27%",
      "change_24h": "+2.68%",
      "change_7d": "-21.71%",
      "market_cap": "$479,232,754",
      "volume_24h": "$67,442,355",
      "trend_24h": "up",
      "trend_7d": "down"
    },
    {
      "rank": "0",
      "name": "Livepeer",
      "symbol": "LPT",
      "logo": "",
      "price": "$6.22",
      "change_1h": "-0.22%",
      "change_24h": "+4.66%",
      "change_7d": "+5.40%",
      "market_cap": "$261,988,617",
      "volume_24h": "$111,601,510",
      "trend_24h": "up",
      "trend_7d": "up"
    },
    {
      "rank": "0",
      "name": "Safe",
      "symbol": "SAFE",
      "logo": "",
      "price": "$0.419502",
      "change_1h": "+0.85%",
      "change_24h": "+5.65%",
      "change_7d": "+4.04%",
      "market_cap": "$254,651,178",
      "volume_24h": "$52,141,441",
      "trend_24h": "up",
      "trend_7d": "up"
    },
    {
      "rank": "0",
      "name": "Peanut the Squirrel",
      "symbol": "PNUT",
      "logo": "",
      "price": "$0.221186",
      "change_1h": "+0.52%",
      "change_24h": "-1.26%",
      "change_7d": "-0.70%",
      "market_cap": "$221,153,014",
      "volume_24h": "$81,632,552",
      "trend_24h": "down",
      "trend_7d": "down"
    },
    {
      "rank": "0",
      "name": "Moo Deng (moodengsol.com)",
      "symbol": "MOODENG",
      "logo": "",
      "price": "$0.183888",
      "change_1h": "+1.55%",
      "change_24h": "+4.95%",
      "change_7d": "+24.08%",
      "market_cap": "$182,043,909",
      "volume_24h": "$158,454,763",
      "trend_24h": "up",
      "trend_7d": "up"
    },
    {
      "rank": "0",
      "name": "Neiro (First Neiro On Ethereum)",
      "symbol": "NEIRO",
      "logo": "",
      "price": "$0.000419",
      "change_1h": "+0.53%",
      "change_24h": "-3.27%",
      "change_7d": "+12.44%",
      "market_cap": "$176,088,139",
      "volume_24h": "$80,263,496",
      "trend_24h": "down",
      "trend_7d": "up"
    },
    {
      "rank": "0",
      "name": "ai16z",
      "symbol": "AI16Z",
      "logo": "",
      "price": "$0.151787",
      "change_1h": "-0.26%",
      "change_24h": "+1.55%",
      "change_7d": "+3.50%",
      "market_cap": "$166,965,873",
      "volume_24h": "$99,592,942",
      "trend_24h": "up",
      "trend_7d": "up"
    },
    {
      "rank": "0",
      "name": "Fasttoken",
      "symbol": "FTN",
      "logo": "",
      "price": "$4.44",
      "change_1h": "-0.02%",
      "change_24h": "-0.01%",
      "change_7d": "+0.67%",
      "market_cap": "$1,938,297,019",
      "volume_24h": "$56,668,017",
      "trend_24h": "down",
      "trend_7d": "up"
    },
    {
      "rank": "0",
      "name": "Sahara AI",
      "symbol": "SAHARA",
      "logo": "",
      "price": "$0.081099",
      "change_1h": "+0.27%",
      "change_24h": "-1.03%",
      "change_7d": "-7.68%",
      "market_cap": "$165,441,327",
      "volume_24h": "$89,458,974",
      "trend_24h": "down",
      "trend_7d": "down"
    },
    {
      "rank": "0",
      "name": "48 Club Token",
      "symbol": "KOGE",
      "logo": "",
      "price": "$48.01",
      "change_1h": "-0.01%",
      "change_24h": "-0.02%",
      "change_7d": "+0.00%",
      "market_cap": "$162,668,416",
      "volume_24h": "$639,071,950",
      "trend_24h": "down",
      "trend_7d": "up"
    },
    {
      "rank": "0",
      "name": "Humanity Protocol",
      "symbol": "H",
      "logo": "",
      "price": "$0.081386",
      "change_1h": "+4.53%",
      "change_24h": "-20.18%",
      "change_7d": "+282.73%",
      "market_cap": "$148,529,706",
      "volume_24h": "$252,089,744",
      "trend_24h": "down",
      "trend_7d": "up"
    },
    {
      "rank": "0",
      "name": "FUNToken",
      "symbol": "FUN",
      "logo": "",
      "price": "$0.013453",
      "change_1h": "+0.67%",
      "change_24h": "-0.87%",
      "change_7d": "+34.76%",
      "market_cap": "$145,538,396",
      "volume_24h": "$76,362,063",
      "trend_24h": "down",
      "trend_7d": "up"
    },
    {
      "rank": "0",
      "name": "AUSD",
      "symbol": "AUSD",
      "logo": "",
      "price": "$0.999811",
      "change_1h": "+0.00%",
      "change_24h": "-0.01%",
      "change_7d": "+0.01%",
      "market_cap": "$128,881,501",
      "volume_24h": "$56,344,135",
      "trend_24h": "down",
      "trend_7d": "up"
    },
    {
      "rank": "0",
      "name": "aixbt",
      "symbol": "AIXBT",
      "logo": "",
      "price": "$0.130331",
      "change_1h": "+0.09%",
      "change_24h": "+3.65%",
      "change_7d": "-2.90%",
      "market_cap": "$123,263,659",
      "volume_24h": "$60,523,623",
      "trend_24h": "up",
      "trend_7d": "down"
    },
    {
      "rank": "0",
      "name": "Stratis [New]",
      "symbol": "STRAX",
      "logo": "",
      "price": "$0.050098",
      "change_1h": "-0.17%",
      "change_24h": "+4.41%",
      "change_7d": "+15.99%",
      "market_cap": "$99,280,560",
      "volume_24h": "$58,398,332",
      "trend_24h": "up",
      "trend_7d": "up"
    },
    {
      "rank": "0",
      "name": "Velo",
      "symbol": "VELO",
      "logo": "",
      "price": "$0.013389",
      "change_1h": "+0.34%",
      "change_24h": "-1.90%",
      "change_7d": "-0.32%",
      "market_cap": "$98,947,639",
      "volume_24h": "$117,457,746",
      "trend_24h": "down",
      "trend_7d": "down"
    },
    {
      "rank": "0",
      "name": "CARV",
      "symbol": "CARV",
      "logo": "",
      "price": "$0.295334",
      "change_1h": "-1.38%",
      "change_24h": "+14.40%",
      "change_7d": "+24.93%",
      "market_cap": "$86,661,519",
      "volume_24h": "$341,769,740",
      "trend_24h": "up",
      "trend_7d": "up"
    },
    {
      "rank": "0",
      "name": "Newton Protocol",
      "symbol": "NEWT",
      "logo": "",
      "price": "$0.326313",
      "change_1h": "-0.30%",
      "change_24h": "-2.97%",
      "change_7d": "-16.39%",
      "market_cap": "$70,157,288",
      "volume_24h": "$206,678,003",
      "trend_24h": "down",
      "trend_7d": "down"
    },
    {
      "rank": "0",
      "name": "EGL1",
      "symbol": "EGL1",
      "logo": "",
      "price": "$0.068648",
      "change_1h": "-3.43%",
      "change_24h": "-14.43%",
      "change_7d": "-0.35%",
      "market_cap": "$68,648,476",
      "volume_24h": "$121,032,138",
      "trend_24h": "down",
      "trend_7d": "down"
    },
    {
      "rank": "0",
      "name": "Huma Finance",
      "symbol": "HUMA",
      "logo": "",
      "price": "$0.030913",
      "change_1h": "+0.82%",
      "change_24h": "-1.23%",
      "change_7d": "-6.25%",
      "market_cap": "$53,582,977",
      "volume_24h": "$63,652,924",
      "trend_24h": "down",
      "trend_7d": "down"
    },
    {
      "rank": "0",
      "name": "Seraph",
      "symbol": "SERAPH",
      "logo": "",
      "price": "$0.194367",
      "change_1h": "+0.53%",
      "change_24h": "+1.31%",
      "change_7d": "+2.45%",
      "market_cap": "$46,551,601",
      "volume_24h": "$82,886,339",
      "trend_24h": "up",
      "trend_7d": "up"
    },
    {
      "rank": "0",
      "name": "Strike",
      "symbol": "STRK",
      "logo": "",
      "price": "$7.85",
      "change_1h": "+2.89%",
      "change_24h": "-5.05%",
      "change_7d": "+36.47%",
      "market_cap": "$44,013,838",
      "volume_24h": "$69,830,065",
      "trend_24h": "down",
      "trend_7d": "up"
    },
    {
      "rank": "0",
      "name": "Impossible Cloud Network",
      "symbol": "ICNT",
      "logo": "",
      "price": "$0.244057",
      "change_1h": "+3.15%",
      "change_24h": "-6.05%",
      "change_7d": "-59.88%",
      "market_cap": "$40,812,662",
      "volume_24h": "$52,102,096",
      "trend_24h": "down",
      "trend_7d": "down"
    },
    {
      "rank": "0",
      "name": "Roam",
      "symbol": "ROAM",
      "logo": "",
      "price": "$0.124120",
      "change_1h": "+0.31%",
      "change_24h": "-8.84%",
      "change_7d": "-11.73%",
      "market_cap": "$37,468,799",
      "volume_24h": "$77,727,759",
      "trend_24h": "down",
      "trend_7d": "down"
    },
    {
      "rank": "0",
      "name": "GUNZ",
      "symbol": "GUN",
      "logo": "",
      "price": "$0.035852",
      "change_1h": "-0.67%",
      "change_24h": "+12.52%",
      "change_7d": "+55.29%",
      "market_cap": "$34,220,853",
      "volume_24h": "$75,262,777",
      "trend_24h": "up",
      "trend_7d": "up"
    },
    {
      "rank": "0",
      "name": "Bubblemaps",
      "symbol": "BMT",
      "logo": "",
      "price": "$0.087909",
      "change_1h": "+1.65%",
      "change_24h": "-34.69%",
      "change_7d": "-36.36%",
      "market_cap": "$31,636,470",
      "volume_24h": "$157,699,116",
      "trend_24h": "down",
      "trend_7d": "down"
    },
    {
      "rank": "0",
      "name": "Bedrock",
      "symbol": "BR",
      "logo": "",
      "price": "$0.128044",
      "change_1h": "+0.01%",
      "change_24h": "+0.02%",
      "change_7d": "+60.80%",
      "market_cap": "$26,889,321",
      "volume_24h": "$4,276,208,950",
      "trend_24h": "up",
      "trend_7d": "up"
    },
    {
      "rank": "0",
      "name": "Bulla",
      "symbol": "BULLA",
      "logo": "",
      "price": "$0.072511",
      "change_1h": "+0.51%",
      "change_24h": "-4.91%",
      "change_7d": "-34.06%",
      "market_cap": "$20,303,172",
      "volume_24h": "$84,573,343",
      "trend_24h": "down",
      "trend_7d": "down"
    },
    {
      "rank": "0",
      "name": "Hifi Finance",
      "symbol": "HIFI",
      "logo": "",
      "price": "$0.084079",
      "change_1h": "-3.18%",
      "change_24h": "-35.59%",
      "change_7d": "-34.15%",
      "market_cap": "$11,923,824",
      "volume_24h": "$60,421,613",
      "trend_24h": "down",
      "trend_7d": "down"
    },
    {
      "rank": "0",
      "name": "Quq",
      "symbol": "QUQ",
      "logo": "",
      "price": "$0.002755",
      "change_1h": "+0.01%",
      "change_24h": "+0.00%",
      "change_7d": "-0.01%",
      "market_cap": "$2,755,480",
      "volume_24h": "$232,076,977",
      "trend_24h": "up",
      "trend_7d": "down"
    },
    {
      "rank": "0",
      "name": "StormX",
      "symbol": "STMX",
      "logo": "",
      "price": "$0.000117",
      "change_1h": "+2.39%",
      "change_24h": "+26.10%",
      "change_7d": "-91.36%",
      "market_cap": "$1,451,053",
      "volume_24h": "$366,522,156",
      "trend_24h": "up",
      "trend_7d": "down"
    },
    {
      "rank": "0",
      "name": "Tether USD Bridged ZED20",
      "symbol": "USDT.z",
      "logo": "",
      "price": "$1.00",
      "change_1h": "+0.01%",
      "change_24h": "+0.00%",
      "change_7d": "+0.02%",
      "market_cap": "$0",
      "volume_24h": "$63,926,019",
      "trend_24h": "up",
      "trend_7d": "up"
    },
    {
      "rank": "0",
      "name": "Wayfinder",
      "symbol": "PROMPT",
      "logo": "",
      "price": "$0.119313",
      "change_1h": "+0.19%",
      "change_24h": "-8.96%",
      "change_7d": "-12.53%",
      "market_cap": "$0",
      "volume_24h": "$51,689,877",
      "trend_24h": "down",
      "trend_7d": "down"
    }
  ],
  "meta": {
    "sources": [
      "CoinMarketCap"
    ],
    "timestamp": "2025-07-05T22:09:32.175522+00:00",
    "count": 89,
    "pages_scraped": 40,
    "volume_filter": "$50.0M+",
    "lastUpdated": "2025-07-05T22:10:59.050338+00:00"
  }
}