{
  "indices": {
    "europe": [
      {
        "country": "Allemagne",
        "index_name": "DAX",
        "value": "19 303,53",
        "change": "-6,48 %",
        "changePercent": "-6,48 %",
        "ytdChange": "-3,04 %",
        "opening": "20 641,72",
        "high": "-3,04 %",
        "low": "Voir",
        "trend": "down"
      },
      {
        "country": "Allemagne",
        "index_name": "TECHN. ALL SHARE TR",
        "value": "3 547,85",
        "change": "-5,42 %",
        "changePercent": "-5,42 %",
        "ytdChange": "-5,62 %",
        "opening": "3 751,11",
        "high": "-5,62 %",
        "low": "Voir",
        "trend": "down"
      },
      {
        "country": "Belgique",
        "index_name": "BEL 20",
        "value": "3 876,07",
        "change": "-5,31 %",
        "changePercent": "-5,31 %",
        "ytdChange": "-9,11 %",
        "opening": "4 093,59",
        "high": "-9,11 %",
        "low": "Voir",
        "trend": "down"
      },
      {
        "country": "Espagne",
        "index_name": "IBEX 35",
        "value": "11 646,50",
        "change": "-6,31 %",
        "changePercent": "-6,31 %",
        "ytdChange": "0,44 %",
        "opening": "12 430,60",
        "high": "0,44 %",
        "low": "Voir",
        "trend": "down"
      },
      {
        "country": "France",
        "index_name": "CAC 40",
        "value": "6 859,13",
        "change": "-5,72 %",
        "changePercent": "-5,72 %",
        "ytdChange": "-7,07 %",
        "opening": "7 274,95",
        "high": "-7,07 %",
        "low": "Voir",
        "trend": "down"
      },
      {
        "country": "Italie",
        "index_name": "FTSE MIB",
        "value": "32 253,68",
        "change": "-6,91 %",
        "changePercent": "-6,91 %",
        "ytdChange": "-5,65 %",
        "opening": "34 649,22",
        "high": "-5,65 %",
        "low": "Voir",
        "trend": "down"
      },
      {
        "country": "Pays-Bas",
        "index_name": "AEX",
        "value": "787,73",
        "change": "-6,37 %",
        "changePercent": "-6,37 %",
        "ytdChange": "-10,35 %",
        "opening": "841,29",
        "high": "-10,35 %",
        "low": "Voir",
        "trend": "down"
      },
      {
        "country": "Royaume-Uni",
        "index_name": "FTSE 100",
        "value": "7 647,63",
        "change": "-5,06 %",
        "changePercent": "-5,06 %",
        "ytdChange": "-6,43 %",
        "opening": "8 054,98",
        "high": "-6,43 %",
        "low": "Voir",
        "trend": "down"
      },
      {
        "country": "Royaume-Uni",
        "index_name": "FTSE 250",
        "value": "17 480,42",
        "change": "-4,82 %",
        "changePercent": "-4,82 %",
        "ytdChange": "-15,24 %",
        "opening": "18 365,35",
        "high": "-15,24 %",
        "low": "Voir",
        "trend": "down"
      },
      {
        "country": "Royaume-Uni",
        "index_name": "FTSE 350",
        "value": "4 169,19",
        "change": "-5,03 %",
        "changePercent": "-5,03 %",
        "ytdChange": "-7,57 %",
        "opening": "4 389,97",
        "high": "-7,57 %",
        "low": "",
        "trend": "down"
      },
      {
        "country": "Suisse",
        "index_name": "SMI",
        "value": "10 944,40",
        "change": "-6,05 %",
        "changePercent": "-6,05 %",
        "ytdChange": "-5,66 %",
        "opening": "11 648,83",
        "high": "-5,66 %",
        "low": "Voir",
        "trend": "down"
      },
      {
        "country": "Zone Euro",
        "index_name": "EURO STOXX 50",
        "value": "4 564,42",
        "change": "-6,43 %",
        "changePercent": "-6,43 %",
        "ytdChange": "-6,77 %",
        "opening": "4 878,31",
        "high": "-6,77 %",
        "low": "Voir",
        "trend": "down"
      }
    ],
    "north-america": [
      {
        "country": "États-Unis",
        "index_name": "S&P 500 INDEX",
        "value": "5 074,08",
        "change": "-5,97 %",
        "changePercent": "-5,97 %",
        "ytdChange": "-13,73 %",
        "opening": "5 396,52",
        "high": "-13,73 %",
        "low": "",
        "trend": "down"
      },
      {
        "country": "États-Unis",
        "index_name": "DOW JONES INDUSTRIAL AVERAGE",
        "value": "38 314,86",
        "change": "-5,50 %",
        "changePercent": "-5,50 %",
        "ytdChange": "-9,94 %",
        "opening": "40 545,93",
        "high": "-9,94 %",
        "low": "",
        "trend": "down"
      },
      {
        "country": "États-Unis",
        "index_name": "NASDAQ Composite",
        "value": "15 587,79",
        "change": "-5,82 %",
        "changePercent": "-5,82 %",
        "ytdChange": "-19,28 %",
        "opening": "16 550,61",
        "high": "-19,28 %",
        "low": "Voir",
        "trend": "down"
      },
      {
        "country": "États-Unis",
        "index_name": "NASDAQ 100 INDEX",
        "value": "17 397,70",
        "change": "-6,07 %",
        "changePercent": "-6,07 %",
        "ytdChange": "-17,20 %",
        "opening": "18 521,48",
        "high": "-17,20 %",
        "low": "Voir",
        "trend": "down"
      },
      {
        "country": "États-Unis",
        "index_name": "CBOE VIX INDEX",
        "value": "45,31",
        "change": "0,00 %",
        "changePercent": "0,00 %",
        "ytdChange": "161,15 %",
        "opening": "45,31",
        "high": "161,15 %",
        "low": "",
        "trend": "up"
      }
    ],
    "latin-america": [
      {
        "country": "Argentine",
        "index_name": "BUENOS AIRES MERVAL",
        "value": "2 107 815,91",
        "change": "-7,38 %",
        "changePercent": "-7,38 %",
        "ytdChange": "-16,81 %",
        "opening": "2 275 658,78",
        "high": "-16,81 %",
        "low": "",
        "trend": "down"
      },
      {
        "country": "Brésil",
        "index_name": "NASDAQ Brazil Large Mid Cap Index",
        "value": "689,50",
        "change": "-4,98 %",
        "changePercent": "-4,98 %",
        "ytdChange": "8,76 %",
        "opening": "725,65",
        "high": "8,76 %",
        "low": "",
        "trend": "down"
      },
      {
        "country": "Chili",
        "index_name": "Santiago IGPA",
        "value": "19 928,40",
        "change": "0,20 %",
        "changePercent": "0,20 %",
        "ytdChange": "13,47 %",
        "opening": "19 888,93",
        "high": "13,47 %",
        "low": "",
        "trend": "up"
      },
      {
        "country": "Chili",
        "index_name": "NASDAQ Chile Large Mid Cap Index",
        "value": "695,89",
        "change": "-6,38 %",
        "changePercent": "-6,38 %",
        "ytdChange": "10,76 %",
        "opening": "743,28",
        "high": "10,76 %",
        "low": "",
        "trend": "down"
      },
      {
        "country": "Mexique",
        "index_name": "NASDAQ Mexico Large Mid Cap Index",
        "value": "776,46",
        "change": "-5,39 %",
        "changePercent": "-5,39 %",
        "ytdChange": "6,06 %",
        "opening": "820,72",
        "high": "6,06 %",
        "low": "",
        "trend": "down"
      }
    ],
    "asia": [
      {
        "country": "Chine",
        "index_name": "SHANGHAI COMPOSITE",
        "value": "3 096,58",
        "change": "-7,34 %",
        "changePercent": "-7,34 %",
        "ytdChange": "-7,61 %",
        "opening": "3 342,01",
        "high": "-7,61 %",
        "low": "",
        "trend": "down"
      },
      {
        "country": "Chine",
        "index_name": "CSI 300 INDEX",
        "value": "3 589,44",
        "change": "-7,05 %",
        "changePercent": "-7,05 %",
        "ytdChange": "-8,78 %",
        "opening": "3 861,50",
        "high": "-8,78 %",
        "low": "",
        "trend": "down"
      },
      {
        "country": "Chine",
        "index_name": "CSI 100 INDEX",
        "value": "3 437,94",
        "change": "-6,85 %",
        "changePercent": "-6,85 %",
        "ytdChange": "-7,71 %",
        "opening": "3 690,89",
        "high": "-7,71 %",
        "low": "",
        "trend": "down"
      },
      {
        "country": "Chine",
        "index_name": "SHENZHEN COMPOSITE",
        "value": "1 777,37",
        "change": "-11,77 %",
        "changePercent": "-11,77 %",
        "ytdChange": "-9,20 %",
        "opening": "2 014,59",
        "high": "-9,20 %",
        "low": "",
        "trend": "down"
      },
      {
        "country": "Corée du Sud",
        "index_name": "NASDAQ Korea Large Mid Cap Index",
        "value": "1 024,29",
        "change": "0,64 %",
        "changePercent": "0,64 %",
        "ytdChange": "5,36 %",
        "opening": "1 017,80",
        "high": "5,36 %",
        "low": "",
        "trend": "up"
      },
      {
        "country": "Hong Kong",
        "index_name": "HONG KONG HANG SENG INDIC",
        "value": "19 828,30",
        "change": "-13,22 %",
        "changePercent": "-13,22 %",
        "ytdChange": "-1,15 %",
        "opening": "22 849,81",
        "high": "-1,15 %",
        "low": "",
        "trend": "down"
      },
      {
        "country": "Hong Kong",
        "index_name": "HANG SENG HK COMPOSITE INDEX",
        "value": "2 931,73",
        "change": "-13,64 %",
        "changePercent": "-13,64 %",
        "ytdChange": "-1,73 %",
        "opening": "3 394,73",
        "high": "-1,73 %",
        "low": "",
        "trend": "down"
      },
      {
        "country": "Japon",
        "index_name": "Nikkei 225",
        "value": "31 136,58",
        "change": "-7,83 %",
        "changePercent": "-7,83 %",
        "ytdChange": "-21,95 %",
        "opening": "33 780,58",
        "high": "-21,95 %",
        "low": "",
        "trend": "down"
      },
      {
        "country": "Taïwan",
        "index_name": "TAIEX",
        "value": "19 232,35",
        "change": "-9,70 %",
        "changePercent": "-9,70 %",
        "ytdChange": "-16,68 %",
        "opening": "21 298,22",
        "high": "-16,68 %",
        "low": "",
        "trend": "down"
      },
      {
        "country": "Taïwan",
        "index_name": "NASDAQ Taiwan Large Mid Cap Index",
        "value": "2 680,61",
        "change": "0,00 %",
        "changePercent": "0,00 %",
        "ytdChange": "-9,42 %",
        "opening": "2 680,61",
        "high": "-9,42 %",
        "low": "",
        "trend": "up"
      }
    ],
    "other": [
      {
        "country": "Afrique du Sud",
        "index_name": "NASDAQ South Africa Large Mid Cap Index",
        "value": "962,57",
        "change": "-7,05 %",
        "changePercent": "-7,05 %",
        "ytdChange": "-4,32 %",
        "opening": "1 035,53",
        "high": "-4,32 %",
        "low": "",
        "trend": "down"
      },
      {
        "country": "Australie",
        "index_name": "All Ordinaries Idx",
        "value": "7 524,30",
        "change": "-4,12 %",
        "changePercent": "-4,12 %",
        "ytdChange": "-10,64 %",
        "opening": "7 847,60",
        "high": "-10,64 %",
        "low": "",
        "trend": "down"
      },
      {
        "country": "Australie",
        "index_name": "NASDAQ Australia Large Mid Cap Index",
        "value": "962,63",
        "change": "-6,06 %",
        "changePercent": "-6,06 %",
        "ytdChange": "-7,85 %",
        "opening": "1 024,74",
        "high": "-7,85 %",
        "low": "",
        "trend": "down"
      },
      {
        "country": "Israël",
        "index_name": "NASDAQ Israel Large Mid Cap Index",
        "value": "1 211,58",
        "change": "-1,06 %",
        "changePercent": "-1,06 %",
        "ytdChange": "-3,11 %",
        "opening": "1 224,51",
        "high": "-3,11 %",
        "low": "",
        "trend": "down"
      },
      {
        "country": "Maroc",
        "index_name": "NASDAQ Morocco Large Mid Cap Index",
        "value": "1 365,85",
        "change": "0,32 %",
        "changePercent": "0,32 %",
        "ytdChange": "17,17 %",
        "opening": "1 361,53",
        "high": "17,17 %",
        "low": "",
        "trend": "up"
      },
      {
        "country": "Nouvelle-Zélande",
        "index_name": "NASDAQ New Zealand Large Mid Cap Index",
        "value": "1 133,28",
        "change": "-4,89 %",
        "changePercent": "-4,89 %",
        "ytdChange": "-11,89 %",
        "opening": "1 191,59",
        "high": "-11,89 %",
        "low": "",
        "trend": "down"
      }
    ]
  },
  "top_performers": {
    "daily": {
      "best": [
        {
          "country": "Inde",
          "index_name": "NASDAQ Eurozone Travel & Leisure Lg Md Cap EUR x",
          "value": "961,56",
          "change": "0,00 %",
          "changePercent": "961,56",
          "ytdChange": "0,00 %",
          "opening": "0,00 %",
          "high": "",
          "low": "",
          "trend": "up",
          "region": "asia"
        },
        {
          "country": "Inde",
          "index_name": "NASDAQ Eurozone Financials Lg Md Cap EUR x",
          "value": "946,81",
          "change": "0,00 %",
          "changePercent": "946,81",
          "ytdChange": "0,00 %",
          "opening": "0,00 %",
          "high": "",
          "low": "",
          "trend": "up",
          "region": "asia"
        },
        {
          "country": "Inde",
          "index_name": "NASDAQ Eurozone Auto & Parts Lg Md Cap EUR x",
          "value": "909,17",
          "change": "0,00 %",
          "changePercent": "909,17",
          "ytdChange": "0,00 %",
          "opening": "0,00 %",
          "high": "",
          "low": "",
          "trend": "up",
          "region": "asia"
        }
      ],
      "worst": [
        {
          "country": "Inde",
          "index_name": "NASDAQ Eurozone Banks Lg Md Cap EUR x",
          "value": "672,60",
          "change": "0,00 %",
          "changePercent": "672,60",
          "ytdChange": "0,00 %",
          "opening": "0,00 %",
          "high": "",
          "low": "",
          "trend": "up",
          "region": "asia"
        },
        {
          "country": "Inde",
          "index_name": "NASDAQ Eurozone Real Estate Lg Md Cap EUR x",
          "value": "725,87",
          "change": "0,00 %",
          "changePercent": "725,87",
          "ytdChange": "0,00 %",
          "opening": "0,00 %",
          "high": "",
          "low": "",
          "trend": "up",
          "region": "asia"
        },
        {
          "country": "Inde",
          "index_name": "NASDAQ Japan Financial Svcs x",
          "value": "859,89",
          "change": "-1,54 %",
          "changePercent": "873,36",
          "ytdChange": "-6,64 %",
          "opening": "-6,64 %",
          "high": "",
          "low": "",
          "trend": "down",
          "region": "asia"
        }
      ]
    },
    "ytd": {
      "best": [
        {
          "country": "Argentine",
          "index_name": "BUENOS AIRES MERVAL",
          "value": "2 107 815,91",
          "change": "-7,38 %",
          "changePercent": "-7,38 %",
          "ytdChange": "-16,81 %",
          "opening": "2 275 658,78",
          "high": "-16,81 %",
          "low": "",
          "trend": "down",
          "region": "latin-america",
          "_change_value": 0.0
        },
        {
          "country": "Brésil",
          "index_name": "NASDAQ Brazil Large Mid Cap Index",
          "value": "689,50",
          "change": "-4,98 %",
          "changePercent": "-4,98 %",
          "ytdChange": "8,76 %",
          "opening": "725,65",
          "high": "8,76 %",
          "low": "",
          "trend": "down",
          "region": "latin-america",
          "_change_value": 0.0
        },
        {
          "country": "Chili",
          "index_name": "Santiago IGPA",
          "value": "19 928,40",
          "change": "0,20 %",
          "changePercent": "0,20 %",
          "ytdChange": "13,47 %",
          "opening": "19 888,93",
          "high": "13,47 %",
          "low": "",
          "trend": "up",
          "region": "latin-america",
          "_change_value": 0.0
        }
      ],
      "worst": []
    }
  },
  "meta": {
    "source": "Boursorama",
    "url": "https://www.boursorama.com/bourse/indices/internationaux",
    "timestamp": "2025-04-07T09:41:18.990781+00:00",
    "count": 38,
    "lastUpdated": "2025-04-07T09:41:18.990781+00:00"
  }
}