{
  "daily": {
    "best": [
      {
        "symbol": "",
        "name": "374WATER",
        "last": "0,475 (c)",
        "change": "+35,99%",
        "open": "0,374",
        "high": "0,679",
        "low": "0,374",
        "ytd": "-30,41%",
        "volume": "0",
        "trend": "up",
        "link": "https://www.boursorama.com/cours/SCWO/",
        "market": "STOXX",
        "marketIcon": "<i class=\"fas fa-globe-europe text-xs ml-1\" title=\"STOXX\"></i>"
      },
      {
        "symbol": "",
        "name": "HAOXIN HLDG RG-A",
        "last": "1,620 (c)",
        "change": "+11,72%",
        "open": "1,410",
        "high": "1,680",
        "low": "1,390",
        "ytd": "-47,91%",
        "volume": "0",
        "trend": "up",
        "link": "https://www.boursorama.com/cours/HXHX/",
        "market": "STOXX",
        "marketIcon": "<i class=\"fas fa-globe-europe text-xs ml-1\" title=\"STOXX\"></i>"
      },
      {
        "symbol": "",
        "name": "908 DEVICES",
        "last": "5,960 (c)",
        "change": "+9,56%",
        "open": "5,480",
        "high": "6,020",
        "low": "5,410",
        "ytd": "+170,91%",
        "volume": "0",
        "trend": "up",
        "link": "https://www.boursorama.com/cours/MASS/",
        "market": "STOXX",
        "marketIcon": "<i class=\"fas fa-globe-europe text-xs ml-1\" title=\"STOXX\"></i>"
      },
      {
        "symbol": "",
        "name": "SOITEC",
        "last": "47,400",
        "change": "+6,56%",
        "open": "45,150",
        "high": "47,410",
        "low": "45,100",
        "ytd": "-45,61%",
        "volume": "101822",
        "trend": "up",
        "link": "https://www.boursorama.com/cours/1rPSOI/",
        "sector": "Semiconducteurs",
        "country": "France",
        "country_code": "fr",
        "flag": "<img src=\"flags/fr.svg\" class=\"country-flag\" alt=\"France\" title=\"France\">",
        "market": "STOXX",
        "marketIcon": "<i class=\"fas fa-globe-europe text-xs ml-1\" title=\"STOXX\"></i>"
      },
      {
        "symbol": "",
        "name": "BESI",
        "last": "113,850",
        "change": "+4,55%",
        "open": "111,600",
        "high": "114,100",
        "low": "111,600",
        "ytd": "-13,95%",
        "volume": "86180",
        "trend": "up",
        "link": "https://www.boursorama.com/cours/1rABESI/",
        "sector": "Semiconducteurs",
        "country": "Netherlands",
        "country_code": "nl",
        "flag": "<img src=\"flags/nl.svg\" class=\"country-flag\" alt=\"Netherlands\" title=\"Netherlands\">",
        "market": "STOXX",
        "marketIcon": "<i class=\"fas fa-globe-europe text-xs ml-1\" title=\"STOXX\"></i>"
      },
      {
        "symbol": "",
        "name": "ASM INT",
        "last": "506,000",
        "change": "+4,46%",
        "open": "496,400",
        "high": "506,000",
        "low": "495,700",
        "ytd": "-9,45%",
        "volume": "28209",
        "trend": "up",
        "link": "https://www.boursorama.com/cours/1rAASM/",
        "sector": "Semiconducteurs",
        "country": "Netherlands",
        "country_code": "nl",
        "flag": "<img src=\"flags/nl.svg\" class=\"country-flag\" alt=\"Netherlands\" title=\"Netherlands\">",
        "market": "STOXX",
        "marketIcon": "<i class=\"fas fa-globe-europe text-xs ml-1\" title=\"STOXX\"></i>"
      },
      {
        "symbol": "",
        "name": "BURBERRY GROUP",
        "last": "1 046,000",
        "change": "+4,24%",
        "open": "1 017,500",
        "high": "1 046,000",
        "low": "1 017,500",
        "ytd": "+8,11%",
        "volume": "79916",
        "trend": "up",
        "link": "https://www.boursorama.com/cours/1uBRBY.L/",
        "sector": "Luxe",
        "country": "United Kingdom",
        "country_code": "gb",
        "flag": "<img src=\"flags/gb.svg\" class=\"country-flag\" alt=\"United Kingdom\" title=\"United Kingdom\">",
        "market": "STOXX",
        "marketIcon": "<i class=\"fas fa-globe-europe text-xs ml-1\" title=\"STOXX\"></i>"
      },
      {
        "symbol": "",
        "name": "ASML HLDG",
        "last": "686,600",
        "change": "+3,90%",
        "open": "675,400",
        "high": "686,600",
        "low": "674,400",
        "ytd": "+1,16%",
        "volume": "91919",
        "trend": "up",
        "link": "https://www.boursorama.com/cours/1rAASML/",
        "sector": "Semiconducteurs",
        "country": "Netherlands",
        "country_code": "nl",
        "flag": "<img src=\"flags/nl.svg\" class=\"country-flag\" alt=\"Netherlands\" title=\"Netherlands\">",
        "market": "STOXX",
        "marketIcon": "<i class=\"fas fa-globe-europe text-xs ml-1\" title=\"STOXX\"></i>"
      },
      {
        "symbol": "",
        "name": "ADIDAS",
        "last": "227,000",
        "change": "+3,89%",
        "open": "226,500",
        "high": "227,700",
        "low": "224,800",
        "ytd": "-4,14%",
        "volume": "79719",
        "trend": "up",
        "link": "https://www.boursorama.com/cours/1zADS/",
        "sector": "Luxe",
        "country": "Germany",
        "country_code": "de",
        "flag": "<img src=\"flags/de.svg\" class=\"country-flag\" alt=\"Germany\" title=\"Germany\">",
        "market": "STOXX",
        "marketIcon": "<i class=\"fas fa-globe-europe text-xs ml-1\" title=\"STOXX\"></i>"
      },
      {
        "symbol": "",
        "name": "AIXTRON",
        "last": "12,840",
        "change": "+3,76%",
        "open": "12,640",
        "high": "12,845",
        "low": "12,620",
        "ytd": "-15,64%",
        "volume": "93715",
        "trend": "up",
        "link": "https://www.boursorama.com/cours/1zAIXA/",
        "sector": "Semiconducteurs",
        "country": "Germany",
        "country_code": "de",
        "flag": "<img src=\"flags/de.svg\" class=\"country-flag\" alt=\"Germany\" title=\"Germany\">",
        "market": "STOXX",
        "marketIcon": "<i class=\"fas fa-globe-europe text-xs ml-1\" title=\"STOXX\"></i>"
      }
    ],
    "worst": [
      {
        "symbol": "",
        "name": "RECKITT BENCK GR",
        "last": "117,525",
        "change": "-98,19%",
        "open": "0,000",
        "high": "6 556,000",
        "low": "6 466,000",
        "ytd": "0,00%",
        "volume": "2640097",
        "trend": "down",
        "link": "https://www.boursorama.com/cours/1uRB..L/",
        "sector": "Produits ménagers",
        "country": "United Kingdom",
        "country_code": "gb",
        "flag": "<img src=\"flags/gb.svg\" class=\"country-flag\" alt=\"United Kingdom\" title=\"United Kingdom\">",
        "market": "STOXX",
        "marketIcon": "<i class=\"fas fa-globe-europe text-xs ml-1\" title=\"STOXX\"></i>"
      },
      {
        "symbol": "",
        "name": "LSE GROUP",
        "last": "3 625,250",
        "change": "-58,19%",
        "open": "8 798,936",
        "high": "8 664,000",
        "low": "8 500,000",
        "ytd": "0,00%",
        "volume": "1006310",
        "trend": "down",
        "link": "https://www.boursorama.com/cours/1uLSE.L/",
        "sector": "Banques",
        "country": "United Kingdom",
        "country_code": "gb",
        "flag": "<img src=\"flags/gb.svg\" class=\"country-flag\" alt=\"United Kingdom\" title=\"United Kingdom\">",
        "market": "STOXX",
        "marketIcon": "<i class=\"fas fa-globe-europe text-xs ml-1\" title=\"STOXX\"></i>"
      },
      {
        "symbol": "",
        "name": "23ANDME RG-A",
        "last": "0,606 (c)",
        "change": "-21,26%",
        "open": "0,000",
        "high": "0,000",
        "low": "0,000",
        "ytd": "-81,34%",
        "volume": "0",
        "trend": "down",
        "link": "https://www.boursorama.com/cours/ME/",
        "market": "STOXX",
        "marketIcon": "<i class=\"fas fa-globe-europe text-xs ml-1\" title=\"STOXX\"></i>"
      },
      {
        "symbol": "",
        "name": "AUTO TRD GR RG-144A",
        "last": "811,800",
        "change": "-9,80%",
        "open": "817,000",
        "high": "825,800",
        "low": "796,400",
        "ytd": "+2,80%",
        "volume": "684316",
        "trend": "down",
        "link": "https://www.boursorama.com/cours/1uAUTO.L/",
        "sector": "Automobile",
        "country": "United States",
        "market": "STOXX",
        "marketIcon": "<i class=\"fas fa-globe-europe text-xs ml-1\" title=\"STOXX\"></i>"
      },
      {
        "symbol": "",
        "name": "FRONTLINE",
        "last": "17,545 (c)",
        "change": "-6,40%",
        "open": "18,205",
        "high": "18,210",
        "low": "17,500",
        "ytd": "+23,56%",
        "volume": "1500932",
        "trend": "down",
        "link": "https://www.boursorama.com/cours/FRO/",
        "sector": "Énergie / Pétrole & Gaz",
        "country": "Norway",
        "country_code": "no",
        "flag": "<img src=\"flags/no.svg\" class=\"country-flag\" alt=\"Norway\" title=\"Norway\">",
        "market": "STOXX",
        "marketIcon": "<i class=\"fas fa-globe-europe text-xs ml-1\" title=\"STOXX\"></i>"
      },
      {
        "symbol": "",
        "name": "VONOVIA",
        "last": "27,950",
        "change": "-5,38%",
        "open": "28,300",
        "high": "28,340",
        "low": "27,950",
        "ytd": "-4,67%",
        "volume": "426563",
        "trend": "down",
        "link": "https://www.boursorama.com/cours/1zVNA/",
        "sector": "Immobilier / REITs",
        "country": "Switzerland",
        "country_code": "ch",
        "flag": "<img src=\"flags/ch.svg\" class=\"country-flag\" alt=\"Switzerland\" title=\"Switzerland\">",
        "market": "STOXX",
        "marketIcon": "<i class=\"fas fa-globe-europe text-xs ml-1\" title=\"STOXX\"></i>"
      },
      {
        "symbol": "",
        "name": "EVONIK INDUSTR",
        "last": "19,010",
        "change": "-5,04%",
        "open": "19,110",
        "high": "19,280",
        "low": "19,000",
        "ytd": "+13,63%",
        "volume": "72033",
        "trend": "down",
        "link": "https://www.boursorama.com/cours/1zEVK/",
        "sector": "Matériaux de base / Métaux",
        "country": "Germany",
        "country_code": "de",
        "flag": "<img src=\"flags/de.svg\" class=\"country-flag\" alt=\"Germany\" title=\"Germany\">",
        "market": "STOXX",
        "marketIcon": "<i class=\"fas fa-globe-europe text-xs ml-1\" title=\"STOXX\"></i>"
      },
      {
        "symbol": "",
        "name": "BOVIS HOMES GROU",
        "last": "1 312,500 (c)",
        "change": "-4,96%",
        "open": "1 342,000",
        "high": "1 342,000",
        "low": "1 298,000",
        "ytd": "0,00%",
        "volume": "688364",
        "trend": "down",
        "link": "https://www.boursorama.com/cours/1uBVS.L/",
        "sector": "Immobilier / REITs",
        "country": "United Kingdom",
        "country_code": "gb",
        "flag": "<img src=\"flags/gb.svg\" class=\"country-flag\" alt=\"United Kingdom\" title=\"United Kingdom\">",
        "market": "STOXX",
        "marketIcon": "<i class=\"fas fa-globe-europe text-xs ml-1\" title=\"STOXX\"></i>"
      },
      {
        "symbol": "",
        "name": "LEG IMMOBILIEN",
        "last": "72,000",
        "change": "-4,82%",
        "open": "72,200",
        "high": "72,450",
        "low": "71,900",
        "ytd": "-11,98%",
        "volume": "15733",
        "trend": "down",
        "link": "https://www.boursorama.com/cours/1zLEG/",
        "sector": "Immobilier / REITs",
        "country": "Germany",
        "country_code": "de",
        "flag": "<img src=\"flags/de.svg\" class=\"country-flag\" alt=\"Germany\" title=\"Germany\">",
        "market": "STOXX",
        "marketIcon": "<i class=\"fas fa-globe-europe text-xs ml-1\" title=\"STOXX\"></i>"
      },
      {
        "symbol": "",
        "name": "180 LIFE SCIS",
        "last": "1,040 (c)",
        "change": "-4,59%",
        "open": "1,070",
        "high": "1,119",
        "low": "1,010",
        "ytd": "-42,86%",
        "volume": "0",
        "trend": "down",
        "link": "https://www.boursorama.com/cours/ATNF/",
        "market": "STOXX",
        "marketIcon": "<i class=\"fas fa-globe-europe text-xs ml-1\" title=\"STOXX\"></i>"
      }
    ]
  },
  "ytd": {
    "best": [
      {
        "symbol": "",
        "name": "RHEINMETALL",
        "last": "1 853,000",
        "change": "-2,37%",
        "open": "1 902,000",
        "high": "1 916,500",
        "low": "1 816,500",
        "ytd": "+201,50%",
        "volume": "66631",
        "trend": "down",
        "link": "https://www.boursorama.com/cours/1zRHM/",
        "sector": "Aéronautique, Défense & Technologies industrielles",
        "country": "Germany",
        "country_code": "de",
        "flag": "<img src=\"flags/de.svg\" class=\"country-flag\" alt=\"Germany\" title=\"Germany\">",
        "market": "STOXX",
        "marketIcon": "<i class=\"fas fa-globe-europe text-xs ml-1\" title=\"STOXX\"></i>"
      },
      {
        "symbol": "",
        "name": "908 DEVICES",
        "last": "5,960 (c)",
        "change": "+9,56%",
        "open": "5,480",
        "high": "6,020",
        "low": "5,410",
        "ytd": "+170,91%",
        "volume": "0",
        "trend": "up",
        "link": "https://www.boursorama.com/cours/MASS/",
        "market": "STOXX",
        "marketIcon": "<i class=\"fas fa-globe-europe text-xs ml-1\" title=\"STOXX\"></i>"
      },
      {
        "symbol": "",
        "name": "THYSSENKRUPP",
        "last": "8,852",
        "change": "-0,36%",
        "open": "8,976",
        "high": "8,986",
        "low": "8,780",
        "ytd": "+125,76%",
        "volume": "630548",
        "trend": "down",
        "link": "https://www.boursorama.com/cours/1zTKA/",
        "sector": "Matériaux de base / Métaux",
        "country": "Germany",
        "country_code": "de",
        "flag": "<img src=\"flags/de.svg\" class=\"country-flag\" alt=\"Germany\" title=\"Germany\">",
        "market": "STOXX",
        "marketIcon": "<i class=\"fas fa-globe-europe text-xs ml-1\" title=\"STOXX\"></i>"
      },
      {
        "symbol": "",
        "name": "LEONARDO",
        "last": "54,080",
        "change": "-2,28%",
        "open": "55,600",
        "high": "55,680",
        "low": "53,940",
        "ytd": "+108,56%",
        "volume": "502442",
        "trend": "down",
        "link": "https://www.boursorama.com/cours/1gLDO/",
        "sector": "Aéronautique, Défense & Technologies industrielles",
        "country": "Italy",
        "country_code": "it",
        "flag": "<img src=\"flags/it.svg\" class=\"country-flag\" alt=\"Italy\" title=\"Italy\">",
        "market": "STOXX",
        "marketIcon": "<i class=\"fas fa-globe-europe text-xs ml-1\" title=\"STOXX\"></i>"
      },
      {
        "symbol": "",
        "name": "THALES",
        "last": "269,700",
        "change": "-0,99%",
        "open": "273,500",
        "high": "274,400",
        "low": "267,200",
        "ytd": "+94,52%",
        "volume": "30805",
        "trend": "down",
        "link": "https://www.boursorama.com/cours/1rPHO/",
        "sector": "Aéronautique, Défense & Technologies industrielles",
        "country": "France",
        "country_code": "fr",
        "flag": "<img src=\"flags/fr.svg\" class=\"country-flag\" alt=\"France\" title=\"France\">",
        "market": "STOXX",
        "marketIcon": "<i class=\"fas fa-globe-europe text-xs ml-1\" title=\"STOXX\"></i>"
      },
      {
        "symbol": "",
        "name": "36KR HLDG ADS",
        "last": "5,800 (c)",
        "change": "-0,85%",
        "open": "5,780",
        "high": "5,980",
        "low": "5,780",
        "ytd": "+81,82%",
        "volume": "0",
        "trend": "down",
        "link": "https://www.boursorama.com/cours/KRKR/",
        "market": "STOXX",
        "marketIcon": "<i class=\"fas fa-globe-europe text-xs ml-1\" title=\"STOXX\"></i>"
      },
      {
        "symbol": "",
        "name": "SOCIETE GENERALE",
        "last": "48,040",
        "change": "+0,69%",
        "open": "48,440",
        "high": "48,460",
        "low": "47,940",
        "ytd": "+76,88%",
        "volume": "112781",
        "trend": "up",
        "link": "https://www.boursorama.com/cours/1rPGLE/",
        "sector": "Banques",
        "country": "France",
        "country_code": "fr",
        "flag": "<img src=\"flags/fr.svg\" class=\"country-flag\" alt=\"France\" title=\"France\">",
        "market": "STOXX",
        "marketIcon": "<i class=\"fas fa-globe-europe text-xs ml-1\" title=\"STOXX\"></i>"
      },
      {
        "symbol": "",
        "name": "SIEMENS ENERGY",
        "last": "85,900",
        "change": "+0,21%",
        "open": "87,640",
        "high": "87,660",
        "low": "85,540",
        "ytd": "+70,50%",
        "volume": "327110",
        "trend": "up",
        "link": "https://www.boursorama.com/cours/1zENR/",
        "sector": "Green Tech / Clean Energy",
        "country": "Germany",
        "country_code": "de",
        "flag": "<img src=\"flags/de.svg\" class=\"country-flag\" alt=\"Germany\" title=\"Germany\">",
        "market": "STOXX",
        "marketIcon": "<i class=\"fas fa-globe-europe text-xs ml-1\" title=\"STOXX\"></i>"
      },
      {
        "symbol": "",
        "name": "2SEVENTY BIO",
        "last": "5,000 (c)",
        "change": "0,00%",
        "open": "0,000",
        "high": "0,000",
        "low": "0,000",
        "ytd": "+70,07%",
        "volume": "0",
        "trend": "neutral",
        "link": "https://www.boursorama.com/cours/TSVT/",
        "market": "STOXX",
        "marketIcon": "<i class=\"fas fa-globe-europe text-xs ml-1\" title=\"STOXX\"></i>"
      },
      {
        "symbol": "",
        "name": "COMMERZBANK",
        "last": "26,630",
        "change": "+0,34%",
        "open": "26,900",
        "high": "26,900",
        "low": "26,600",
        "ytd": "+69,35%",
        "volume": "135662",
        "trend": "up",
        "link": "https://www.boursorama.com/cours/1zCBK/",
        "sector": "Banques",
        "country": "Germany",
        "country_code": "de",
        "flag": "<img src=\"flags/de.svg\" class=\"country-flag\" alt=\"Germany\" title=\"Germany\">",
        "market": "STOXX",
        "marketIcon": "<i class=\"fas fa-globe-europe text-xs ml-1\" title=\"STOXX\"></i>"
      }
    ],
    "worst": [
      {
        "symbol": "",
        "name": "22ND CENTURY",
        "last": "0,775 (c)",
        "change": "-3,88%",
        "open": "0,770",
        "high": "0,802",
        "low": "0,765",
        "ytd": "-85,41%",
        "volume": "0",
        "trend": "down",
        "link": "https://www.boursorama.com/cours/XXII/",
        "market": "STOXX",
        "marketIcon": "<i class=\"fas fa-globe-europe text-xs ml-1\" title=\"STOXX\"></i>"
      },
      {
        "symbol": "",
        "name": "23ANDME RG-A",
        "last": "0,606 (c)",
        "change": "-21,26%",
        "open": "0,000",
        "high": "0,000",
        "low": "0,000",
        "ytd": "-81,34%",
        "volume": "0",
        "trend": "down",
        "link": "https://www.boursorama.com/cours/ME/",
        "market": "STOXX",
        "marketIcon": "<i class=\"fas fa-globe-europe text-xs ml-1\" title=\"STOXX\"></i>"
      },
      {
        "symbol": "",
        "name": "TRILLER GRP",
        "last": "0,615 (c)",
        "change": "+0,79%",
        "open": "0,630",
        "high": "0,677",
        "low": "0,610",
        "ytd": "-74,17%",
        "volume": "0",
        "trend": "up",
        "link": "https://www.boursorama.com/cours/ILLR/",
        "sector": "IT Services",
        "country": "United States",
        "market": "STOXX",
        "marketIcon": "<i class=\"fas fa-globe-europe text-xs ml-1\" title=\"STOXX\"></i>"
      },
      {
        "symbol": "",
        "name": "5E ADV MAT",
        "last": "4,380 (c)",
        "change": "0,00%",
        "open": "4,420",
        "high": "4,500",
        "low": "4,330",
        "ytd": "-70,24%",
        "volume": "0",
        "trend": "neutral",
        "link": "https://www.boursorama.com/cours/FEAM/",
        "market": "STOXX",
        "marketIcon": "<i class=\"fas fa-globe-europe text-xs ml-1\" title=\"STOXX\"></i>"
      },
      {
        "symbol": "",
        "name": "60 DEGREES PH",
        "last": "2,300 (c)",
        "change": "-2,54%",
        "open": "2,360",
        "high": "2,446",
        "low": "2,253",
        "ytd": "-64,34%",
        "volume": "0",
        "trend": "down",
        "link": "https://www.boursorama.com/cours/SXTP/",
        "market": "STOXX",
        "marketIcon": "<i class=\"fas fa-globe-europe text-xs ml-1\" title=\"STOXX\"></i>"
      },
      {
        "symbol": "",
        "name": "HAOXIN HLDG RG-A",
        "last": "1,620 (c)",
        "change": "+11,72%",
        "open": "1,410",
        "high": "1,680",
        "low": "1,390",
        "ytd": "-47,91%",
        "volume": "0",
        "trend": "up",
        "link": "https://www.boursorama.com/cours/HXHX/",
        "market": "STOXX",
        "marketIcon": "<i class=\"fas fa-globe-europe text-xs ml-1\" title=\"STOXX\"></i>"
      },
      {
        "symbol": "",
        "name": "SOITEC",
        "last": "47,400",
        "change": "+6,56%",
        "open": "45,150",
        "high": "47,410",
        "low": "45,100",
        "ytd": "-45,61%",
        "volume": "101822",
        "trend": "up",
        "link": "https://www.boursorama.com/cours/1rPSOI/",
        "sector": "Semiconducteurs",
        "country": "France",
        "country_code": "fr",
        "flag": "<img src=\"flags/fr.svg\" class=\"country-flag\" alt=\"France\" title=\"France\">",
        "market": "STOXX",
        "marketIcon": "<i class=\"fas fa-globe-europe text-xs ml-1\" title=\"STOXX\"></i>"
      },
      {
        "symbol": "",
        "name": "PUMA",
        "last": "24,160",
        "change": "+2,76%",
        "open": "23,900",
        "high": "24,170",
        "low": "23,810",
        "ytd": "-45,54%",
        "volume": "99876",
        "trend": "up",
        "link": "https://www.boursorama.com/cours/1zPUM/",
        "sector": "Luxe",
        "country": "Germany",
        "country_code": "de",
        "flag": "<img src=\"flags/de.svg\" class=\"country-flag\" alt=\"Germany\" title=\"Germany\">",
        "market": "STOXX",
        "marketIcon": "<i class=\"fas fa-globe-europe text-xs ml-1\" title=\"STOXX\"></i>"
      },
      {
        "symbol": "",
        "name": "180 LIFE SCIS",
        "last": "1,040 (c)",
        "change": "-4,59%",
        "open": "1,070",
        "high": "1,119",
        "low": "1,010",
        "ytd": "-42,86%",
        "volume": "0",
        "trend": "down",
        "link": "https://www.boursorama.com/cours/ATNF/",
        "market": "STOXX",
        "marketIcon": "<i class=\"fas fa-globe-europe text-xs ml-1\" title=\"STOXX\"></i>"
      },
      {
        "symbol": "",
        "name": "1-800-FLOWERS.COM-A",
        "last": "4,790 (c)",
        "change": "+1,05%",
        "open": "4,770",
        "high": "4,900",
        "low": "4,720",
        "ytd": "-41,37%",
        "volume": "0",
        "trend": "up",
        "link": "https://www.boursorama.com/cours/FLWS/",
        "market": "STOXX",
        "marketIcon": "<i class=\"fas fa-globe-europe text-xs ml-1\" title=\"STOXX\"></i>"
      }
    ]
  },
  "meta": {
    "timestamp": "2025-05-29T07:35:03.374803+00:00",
    "count": 631,
    "description": "Top performers du marché STOXX"
  }
}